partoserial/probador.v
module probador(
    input data_out_conduc,
    input data_out_estruct,
    output reg[7:0]data_in,
    output reg valid_in,
    output reg reset,
    output reg clk_8f);

    reg clk_f;
    reg clk_4f;
    reg clk_ff;
    reg cond;
    reg estruct;
   initial begin
    $dumpfile("bancopruebas.vcd");
    $dumpvars;
    $display("\t\ttime,\t reset, clk_f, clk_8f, valid_in, data_in, data_out_cond, data_out_estruct");

    $monitor($time,"\t%b,\t%b,\t%b,\t%b,\t%h,\t%b,\t%b",reset, clk_f, clk_8f, valid_in, data_in, data_out_conduc, data_out_estruct);
    reset<='b0;
    data_in<='b0;
    valid_in<='b0;
    
    @(posedge clk_f);
	reset<='b1;
    valid_in<='b1;
	data_in<=data_in+1;
    
    repeat (10) begin
    @(posedge clk_f);
    data_in<=data_in+1;
    end

    @(posedge clk_f);
    valid_in<='b0;
    data_in<=data_in+1;

    repeat (2) begin
    @(posedge clk_f);
    data_in<=data_in+1;
    end
     
    $finish;
      
   end

    initial begin
    clk_8f <=0;
    clk_4f <=0;
    clk_f <=0;  
    clk_ff<=0;  
    
    end
    always #2 clk_8f <=~clk_8f;
    
    always @(posedge clk_8f)begin
        clk_4f<=~clk_4f;
    end

    always @(posedge clk_4f)begin
        clk_ff<=~clk_ff;
    end

    always @(posedge clk_ff)begin
        clk_f<=~clk_f;
    end
    
   always @(posedge clk_8f) begin
      cond<=data_out_conduc;
      estruct<=data_out_estruct;
      if (reset) begin
      if(cond==estruct)
         $display("Las descripciones son iguales en ambas salidas");   
      end 
   end

endmodule

partoserial/partoserialSynth.v
/* Generated by Yosys 0.8 (git sha1 UNKNOWN, clang 6.0.0-1ubuntu2 -fPIC -Os) */
`include "./CMOS/cmos_cells.v"

module partoserialSynth(data_in, valid_in, reset, clk_8f, data_out);
  wire [3:0] _00_;
  wire _01_;
  wire _02_;
  wire _03_;
  wire _04_;
  wire _05_;
  wire _06_;
  wire _07_;
  wire _08_;
  wire _09_;
  wire _10_;
  wire _11_;
  wire _12_;
  wire _13_;
  wire _14_;
  wire _15_;
  wire _16_;
  wire _17_;
  wire _18_;
  wire _19_;
  wire _20_;
  wire _21_;
  wire _22_;
  wire _23_;
  wire _24_;
  wire _25_;
  wire _26_;
  wire _27_;
  wire _28_;
  wire _29_;
  wire _30_;
  wire _31_;
  wire _32_;
  wire _33_;
  wire _34_;
  wire _35_;
  wire _36_;
  wire _37_;
  wire _38_;
  wire _39_;
  wire _40_;
  wire _41_;
  wire _42_;
  wire _43_;
  wire _44_;
  wire _45_;
  input clk_8f;
  wire [3:0] contador;
  input [7:0] data_in;
  output data_out;
  input reset;
  input valid_in;
  NOT _46_ (
    .A(contador[3]),
    .Y(_02_)
  );
  NOT _47_ (
    .A(reset),
    .Y(_03_)
  );
  NOT _48_ (
    .A(data_in[6]),
    .Y(_04_)
  );
  NOT _49_ (
    .A(data_in[7]),
    .Y(_05_)
  );
  NOT _50_ (
    .A(contador[0]),
    .Y(_06_)
  );
  NOT _51_ (
    .A(contador[1]),
    .Y(_07_)
  );
  NOT _52_ (
    .A(contador[2]),
    .Y(_08_)
  );
  NOR _53_ (
    .A(_03_),
    .B(contador[0]),
    .Y(_00_[0])
  );
  NOR _54_ (
    .A(_06_),
    .B(_07_),
    .Y(_09_)
  );
  NOR _55_ (
    .A(contador[0]),
    .B(contador[1]),
    .Y(_10_)
  );
  NOT _56_ (
    .A(_10_),
    .Y(_11_)
  );
  NAND _57_ (
    .A(reset),
    .B(_11_),
    .Y(_12_)
  );
  NOR _58_ (
    .A(_09_),
    .B(_12_),
    .Y(_00_[1])
  );
  NOR _59_ (
    .A(contador[2]),
    .B(_09_),
    .Y(_13_)
  );
  NAND _60_ (
    .A(contador[2]),
    .B(_09_),
    .Y(_14_)
  );
  NAND _61_ (
    .A(reset),
    .B(_14_),
    .Y(_15_)
  );
  NOR _62_ (
    .A(_13_),
    .B(_15_),
    .Y(_00_[2])
  );
  NOR _63_ (
    .A(_02_),
    .B(_15_),
    .Y(_00_[3])
  );
  NAND _64_ (
    .A(reset),
    .B(valid_in),
    .Y(_16_)
  );
  NOR _65_ (
    .A(data_in[4]),
    .B(_16_),
    .Y(_17_)
  );
  NOR _66_ (
    .A(contador[2]),
    .B(_17_),
    .Y(_18_)
  );
  NOR _67_ (
    .A(_08_),
    .B(_16_),
    .Y(_19_)
  );
  NOT _68_ (
    .A(_19_),
    .Y(_20_)
  );
  NAND _69_ (
    .A(data_in[0]),
    .B(_19_),
    .Y(_21_)
  );
  NAND _70_ (
    .A(contador[1]),
    .B(_21_),
    .Y(_22_)
  );
  NOR _71_ (
    .A(_18_),
    .B(_22_),
    .Y(_23_)
  );
  NOR _72_ (
    .A(data_in[2]),
    .B(_20_),
    .Y(_24_)
  );
  NOR _73_ (
    .A(_04_),
    .B(_16_),
    .Y(_25_)
  );
  NOR _74_ (
    .A(contador[2]),
    .B(_25_),
    .Y(_26_)
  );
  NOR _75_ (
    .A(_24_),
    .B(_26_),
    .Y(_27_)
  );
  NOR _76_ (
    .A(contador[1]),
    .B(_27_),
    .Y(_28_)
  );
  NOR _77_ (
    .A(_23_),
    .B(_28_),
    .Y(_29_)
  );
  NOR _78_ (
    .A(_06_),
    .B(_29_),
    .Y(_30_)
  );
  NOR _79_ (
    .A(contador[1]),
    .B(_16_),
    .Y(_31_)
  );
  NOR _80_ (
    .A(_05_),
    .B(contador[2]),
    .Y(_32_)
  );
  NAND _81_ (
    .A(data_in[3]),
    .B(contador[2]),
    .Y(_33_)
  );
  NOT _82_ (
    .A(_33_),
    .Y(_34_)
  );
  NOR _83_ (
    .A(_32_),
    .B(_34_),
    .Y(_35_)
  );
  NAND _84_ (
    .A(_31_),
    .B(_35_),
    .Y(_36_)
  );
  NOR _85_ (
    .A(data_in[5]),
    .B(_16_),
    .Y(_37_)
  );
  NOR _86_ (
    .A(contador[2]),
    .B(_37_),
    .Y(_38_)
  );
  NAND _87_ (
    .A(data_in[1]),
    .B(_19_),
    .Y(_39_)
  );
  NOR _88_ (
    .A(_07_),
    .B(_38_),
    .Y(_40_)
  );
  NAND _89_ (
    .A(_39_),
    .B(_40_),
    .Y(_41_)
  );
  NAND _90_ (
    .A(_36_),
    .B(_41_),
    .Y(_42_)
  );
  NAND _91_ (
    .A(_06_),
    .B(_42_),
    .Y(_43_)
  );
  NOR _92_ (
    .A(contador[3]),
    .B(_03_),
    .Y(_44_)
  );
  NAND _93_ (
    .A(_43_),
    .B(_44_),
    .Y(_45_)
  );
  NOR _94_ (
    .A(_30_),
    .B(_45_),
    .Y(_01_)
  );
  DFF _95_ (
    .C(clk_8f),
    .D(_01_),
    .Q(data_out)
  );
  DFF _96_ (
    .C(clk_8f),
    .D(_00_[0]),
    .Q(contador[0])
  );
  DFF _97_ (
    .C(clk_8f),
    .D(_00_[1]),
    .Q(contador[1])
  );
  DFF _98_ (
    .C(clk_8f),
    .D(_00_[2]),
    .Q(contador[2])
  );
  DFF _99_ (
    .C(clk_8f),
    .D(_00_[3]),
    .Q(contador[3])
  );
endmodule

partoserial/partoserial.v
module partoserial(
    input [7:0]data_in,
    input valid_in,
    input reset,
    input clk_8f,
    output reg data_out);

reg [7:0]data2send;
reg [3:0]contador;

always @(*)begin
//data_out=data2send[7-contador];
    if(reset==0)begin
        data2send='hBC;
    end
    else begin
       if (valid_in==1)
            data2send=data_in;
        else
            data2send='hBC; 
    end
 
end


always @(posedge clk_8f)begin
    if(reset==0)begin
        data_out<='b0;
        //data2send<=data_in;
        contador<=0;
    end
    else begin    
        data_out<=data2send[7-contador];
        contador<=contador+1;
        if(contador==7)begin
            contador<='b0;
        end
    end
end

endmodule

partoserial/bancopruebas.v
`timescale 1ns /100 ps

`include "probador.v"
`include "partoserial.v"
`include "partoserialSynth.v"

module bancopruebas;
    wire[7:0] data_in;
    wire clk_f,clk_8f,reset,valid_in,data_out_conduc,data_out_estruct;
    
    
	partoserial modul_cond(/*AUTOINST*/
			       // Outputs
			       .data_out	(data_out_conduc),
			       // Inputs
			       .data_in		(data_in[7:0]),
			       .valid_in	(valid_in),
			       .reset		(reset),
			       .clk_8f		(clk_8f)); 
	partoserialSynth modul_estruct(/*AUTOINST*/
				       // Outputs
				       .data_out	(data_out_estruct),
				       // Inputs
				       .clk_8f		(clk_8f),
				       .data_in		(data_in[7:0]),
				       .reset		(reset),
				       .valid_in	(valid_in));  
	probador mi_probador(/*AUTOINST*/
			     // Outputs
			     .data_in		(data_in[7:0]),
			     .valid_in		(valid_in),
			     .reset		(reset),
			     .clk_8f		(clk_8f),
			     // Inputs
			     .data_out_conduc	(data_out_conduc),
			     .data_out_estruct	(data_out_estruct));
endmodule

byte_stripping/cmos_cells.v
module BUF(input A,output Y);
assign Y = A;
endmodule

module NOT(input A,output Y);
assign Y = ~A;
endmodule

module NAND(input A, input B, output Y);
assign Y = ~(A & B);
endmodule

module NOR(input A, input B, output Y);
assign Y = ~(A | B);
endmodule

module DFF(input C, input D, output reg Q);
always @(posedge C)
	Q <= D;
endmodule

module DFFSR(input C, input D, input S, input R, output reg Q);
always @(posedge C, posedge S, posedge R)
	if (S)
		Q <= 1'b1;
	else if (R)
		Q <= 1'b0;
	else
		Q <= D;
endmodule

partoserial/bancopruebas.vcd
$date
	Wed May 15 19:08:44 2019
$end
$version
	Icarus Verilog
$end
$timescale
	100ps
$end
$scope module BUF $end
$var wire 1 ! A $end
$var wire 1 " Y $end
$upscope $end
$scope module DFFSR $end
$var wire 1 # C $end
$var wire 1 $ D $end
$var wire 1 % R $end
$var wire 1 & S $end
$var reg 1 ' Q $end
$upscope $end
$scope module bancopruebas $end
$var wire 1 ( valid_in $end
$var wire 1 ) reset $end
$var wire 1 * data_out_estruct $end
$var wire 1 + data_out_conduc $end
$var wire 8 , data_in [7:0] $end
$var wire 1 - clk_8f $end
$scope module mi_probador $end
$var wire 1 * data_out_estruct $end
$var wire 1 + data_out_conduc $end
$var reg 1 . clk_4f $end
$var reg 1 - clk_8f $end
$var reg 1 / clk_f $end
$var reg 1 0 clk_ff $end
$var reg 1 1 cond $end
$var reg 8 2 data_in [7:0] $end
$var reg 1 3 estruct $end
$var reg 1 ) reset $end
$var reg 1 ( valid_in $end
$upscope $end
$scope module modul_cond $end
$var wire 1 - clk_8f $end
$var wire 8 4 data_in [7:0] $end
$var wire 1 ) reset $end
$var wire 1 ( valid_in $end
$var reg 4 5 contador [3:0] $end
$var reg 8 6 data2send [7:0] $end
$var reg 1 + data_out $end
$upscope $end
$scope module modul_estruct $end
$var wire 1 - clk_8f $end
$var wire 8 7 data_in [7:0] $end
$var wire 1 ) reset $end
$var wire 1 ( valid_in $end
$var wire 1 * data_out $end
$var wire 4 8 contador [3:0] $end
$var wire 1 9 _45_ $end
$var wire 1 : _44_ $end
$var wire 1 ; _43_ $end
$var wire 1 < _42_ $end
$var wire 1 = _41_ $end
$var wire 1 > _40_ $end
$var wire 1 ? _39_ $end
$var wire 1 @ _38_ $end
$var wire 1 A _37_ $end
$var wire 1 B _36_ $end
$var wire 1 C _35_ $end
$var wire 1 D _34_ $end
$var wire 1 E _33_ $end
$var wire 1 F _32_ $end
$var wire 1 G _31_ $end
$var wire 1 H _30_ $end
$var wire 1 I _29_ $end
$var wire 1 J _28_ $end
$var wire 1 K _27_ $end
$var wire 1 L _26_ $end
$var wire 1 M _25_ $end
$var wire 1 N _24_ $end
$var wire 1 O _23_ $end
$var wire 1 P _22_ $end
$var wire 1 Q _21_ $end
$var wire 1 R _20_ $end
$var wire 1 S _19_ $end
$var wire 1 T _18_ $end
$var wire 1 U _17_ $end
$var wire 1 V _16_ $end
$var wire 1 W _15_ $end
$var wire 1 X _14_ $end
$var wire 1 Y _13_ $end
$var wire 1 Z _12_ $end
$var wire 1 [ _11_ $end
$var wire 1 \ _10_ $end
$var wire 1 ] _09_ $end
$var wire 1 ^ _08_ $end
$var wire 1 _ _07_ $end
$var wire 1 ` _06_ $end
$var wire 1 a _05_ $end
$var wire 1 b _04_ $end
$var wire 1 c _03_ $end
$var wire 1 d _02_ $end
$var wire 1 e _01_ $end
$var wire 4 f _00_ [3:0] $end
$scope module _46_ $end
$var wire 1 g A $end
$var wire 1 d Y $end
$upscope $end
$scope module _47_ $end
$var wire 1 ) A $end
$var wire 1 c Y $end
$upscope $end
$scope module _48_ $end
$var wire 1 h A $end
$var wire 1 b Y $end
$upscope $end
$scope module _49_ $end
$var wire 1 i A $end
$var wire 1 a Y $end
$upscope $end
$scope module _50_ $end
$var wire 1 j A $end
$var wire 1 ` Y $end
$upscope $end
$scope module _51_ $end
$var wire 1 k A $end
$var wire 1 _ Y $end
$upscope $end
$scope module _52_ $end
$var wire 1 l A $end
$var wire 1 ^ Y $end
$upscope $end
$scope module _53_ $end
$var wire 1 c A $end
$var wire 1 m B $end
$var wire 1 n Y $end
$upscope $end
$scope module _54_ $end
$var wire 1 ` A $end
$var wire 1 _ B $end
$var wire 1 ] Y $end
$upscope $end
$scope module _55_ $end
$var wire 1 o A $end
$var wire 1 p B $end
$var wire 1 \ Y $end
$upscope $end
$scope module _56_ $end
$var wire 1 \ A $end
$var wire 1 [ Y $end
$upscope $end
$scope module _57_ $end
$var wire 1 ) A $end
$var wire 1 [ B $end
$var wire 1 Z Y $end
$upscope $end
$scope module _58_ $end
$var wire 1 ] A $end
$var wire 1 Z B $end
$var wire 1 q Y $end
$upscope $end
$scope module _59_ $end
$var wire 1 r A $end
$var wire 1 ] B $end
$var wire 1 Y Y $end
$upscope $end
$scope module _60_ $end
$var wire 1 s A $end
$var wire 1 ] B $end
$var wire 1 X Y $end
$upscope $end
$scope module _61_ $end
$var wire 1 ) A $end
$var wire 1 X B $end
$var wire 1 W Y $end
$upscope $end
$scope module _62_ $end
$var wire 1 Y A $end
$var wire 1 W B $end
$var wire 1 t Y $end
$upscope $end
$scope module _63_ $end
$var wire 1 d A $end
$var wire 1 W B $end
$var wire 1 u Y $end
$upscope $end
$scope module _64_ $end
$var wire 1 ) A $end
$var wire 1 ( B $end
$var wire 1 V Y $end
$upscope $end
$scope module _65_ $end
$var wire 1 v A $end
$var wire 1 V B $end
$var wire 1 U Y $end
$upscope $end
$scope module _66_ $end
$var wire 1 w A $end
$var wire 1 U B $end
$var wire 1 T Y $end
$upscope $end
$scope module _67_ $end
$var wire 1 ^ A $end
$var wire 1 V B $end
$var wire 1 S Y $end
$upscope $end
$scope module _68_ $end
$var wire 1 S A $end
$var wire 1 R Y $end
$upscope $end
$scope module _69_ $end
$var wire 1 x A $end
$var wire 1 S B $end
$var wire 1 Q Y $end
$upscope $end
$scope module _70_ $end
$var wire 1 y A $end
$var wire 1 Q B $end
$var wire 1 P Y $end
$upscope $end
$scope module _71_ $end
$var wire 1 T A $end
$var wire 1 P B $end
$var wire 1 O Y $end
$upscope $end
$scope module _72_ $end
$var wire 1 z A $end
$var wire 1 R B $end
$var wire 1 N Y $end
$upscope $end
$scope module _73_ $end
$var wire 1 b A $end
$var wire 1 V B $end
$var wire 1 M Y $end
$upscope $end
$scope module _74_ $end
$var wire 1 { A $end
$var wire 1 M B $end
$var wire 1 L Y $end
$upscope $end
$scope module _75_ $end
$var wire 1 N A $end
$var wire 1 L B $end
$var wire 1 K Y $end
$upscope $end
$scope module _76_ $end
$var wire 1 | A $end
$var wire 1 K B $end
$var wire 1 J Y $end
$upscope $end
$scope module _77_ $end
$var wire 1 O A $end
$var wire 1 J B $end
$var wire 1 I Y $end
$upscope $end
$scope module _78_ $end
$var wire 1 ` A $end
$var wire 1 I B $end
$var wire 1 H Y $end
$upscope $end
$scope module _79_ $end
$var wire 1 } A $end
$var wire 1 V B $end
$var wire 1 G Y $end
$upscope $end
$scope module _80_ $end
$var wire 1 a A $end
$var wire 1 ~ B $end
$var wire 1 F Y $end
$upscope $end
$scope module _81_ $end
$var wire 1 !" A $end
$var wire 1 "" B $end
$var wire 1 E Y $end
$upscope $end
$scope module _82_ $end
$var wire 1 E A $end
$var wire 1 D Y $end
$upscope $end
$scope module _83_ $end
$var wire 1 F A $end
$var wire 1 D B $end
$var wire 1 C Y $end
$upscope $end
$scope module _84_ $end
$var wire 1 G A $end
$var wire 1 C B $end
$var wire 1 B Y $end
$upscope $end
$scope module _85_ $end
$var wire 1 #" A $end
$var wire 1 V B $end
$var wire 1 A Y $end
$upscope $end
$scope module _86_ $end
$var wire 1 $" A $end
$var wire 1 A B $end
$var wire 1 @ Y $end
$upscope $end
$scope module _87_ $end
$var wire 1 %" A $end
$var wire 1 S B $end
$var wire 1 ? Y $end
$upscope $end
$scope module _88_ $end
$var wire 1 _ A $end
$var wire 1 @ B $end
$var wire 1 > Y $end
$upscope $end
$scope module _89_ $end
$var wire 1 ? A $end
$var wire 1 > B $end
$var wire 1 = Y $end
$upscope $end
$scope module _90_ $end
$var wire 1 B A $end
$var wire 1 = B $end
$var wire 1 < Y $end
$upscope $end
$scope module _91_ $end
$var wire 1 ` A $end
$var wire 1 < B $end
$var wire 1 ; Y $end
$upscope $end
$scope module _92_ $end
$var wire 1 &" A $end
$var wire 1 c B $end
$var wire 1 : Y $end
$upscope $end
$scope module _93_ $end
$var wire 1 ; A $end
$var wire 1 : B $end
$var wire 1 9 Y $end
$upscope $end
$scope module _94_ $end
$var wire 1 H A $end
$var wire 1 9 B $end
$var wire 1 e Y $end
$upscope $end
$scope module _95_ $end
$var wire 1 - C $end
$var wire 1 e D $end
$var reg 1 * Q $end
$upscope $end
$scope module _96_ $end
$var wire 1 - C $end
$var wire 1 '" D $end
$var reg 1 (" Q $end
$upscope $end
$scope module _97_ $end
$var wire 1 - C $end
$var wire 1 )" D $end
$var reg 1 *" Q $end
$upscope $end
$scope module _98_ $end
$var wire 1 - C $end
$var wire 1 +" D $end
$var reg 1 ," Q $end
$upscope $end
$scope module _99_ $end
$var wire 1 - C $end
$var wire 1 -" D $end
$var reg 1 ." Q $end
$upscope $end
$upscope $end
$upscope $end
$enddefinitions $end
#0
$dumpvars
x."
0-"
x,"
0+"
x*"
0)"
x("
0'"
x&"
0%"
x$"
0#"
x""
0!"
x~
x}
x|
x{
0z
xy
0x
xw
0v
0u
0t
xs
xr
0q
xp
xo
0n
xm
xl
xk
xj
0i
0h
xg
b0 f
0e
xd
1c
1b
1a
x`
x_
x^
x]
x\
x[
1Z
xY
xX
1W
1V
0U
xT
0S
1R
1Q
xP
xO
0N
0M
xL
xK
xJ
xI
xH
0G
0F
1E
0D
1C
1B
0A
x@
1?
x>
x=
x<
x;
0:
19
bx 8
b0 7
b10111100 6
bx 5
b0 4
x3
b0 2
x1
00
0/
0.
0-
b0 ,
x+
x*
0)
0(
x'
z&
z%
z$
z#
z"
z!
$end
#20
0e
0B
19
1'"
1U
1G
1A
b1 f
1n
1:
0W
0V
1x
b1 6
0c
b1 ,
b1 2
b1 4
b1 7
1(
1)
1/
10
0;
0I
1<
1J
1Y
1=
0K
0O
0H
0[
0]
0>
1P
1\
0@
1L
0T
1X
1`
1_
1^
1d
0o
0m
0j
0}
0|
0y
0p
0k
0$"
0""
0~
0{
0w
0s
0r
0l
0&"
0g
b0 5
0+
0*
0("
0*"
0,"
b0 8
0."
1.
1-
#40
0-
#60
1)"
1q
0Z
09
1[
0'"
1H
1;
0\
b10 f
0n
0`
1o
1m
1j
03
01
0.
b1 8
1("
b1 5
1-
#80
0-
#100
00
0e
19
0=
1B
0I
1O
1'"
0H
0;
1>
b11 f
1n
0G
0J
0P
1`
0_
0o
0m
0j
1}
1|
1y
1p
1k
b10 5
0("
b10 8
1*"
1.
1-
#120
0-
#140
1+"
1t
0)"
0q
0Y
09
0'"
1]
1H
1;
b100 f
0n
0`
1o
1m
1j
0.
b11 8
1("
b11 5
1-
#160
0-
#180
0/
10
0I
1+"
0)"
1t
1N
0e
19
1Z
0q
1=
0Q
0B
0O
0K
0W
0R
1'"
0H
0;
0[
0]
0>
1S
b101 f
1n
1G
1J
1P
1\
0L
1X
1`
1_
0^
0o
0m
0j
0}
0|
0y
0p
0k
1$"
1""
1~
1{
1w
1s
1r
1l
b100 5
0("
0*"
b100 8
1,"
1.
1-
#200
0-
#220
1)"
1q
0Z
09
1[
0'"
1H
1;
0\
b110 f
0n
0`
1o
1m
1j
0.
b101 8
1("
b101 5
1-
#240
0-
#260
00
0e
19
0=
1B
1I
1'"
0H
0;
1>
b111 f
1n
0G
0J
1`
0_
0o
0m
0j
1}
1|
1y
1p
1k
b110 5
0("
b110 8
1*"
1.
1-
#280
0-
#300
0+"
0t
1W
1e
0)"
0q
0X
09
0'"
1]
1;
b0 f
0n
0`
1o
1m
1j
0.
b111 8
1("
b111 5
1-
#320
0-
#340
b10 6
0x
1%"
b10 ,
b10 2
b10 4
b10 7
1/
10
0e
0+"
0)"
0t
0N
19
1Z
0q
1Y
1=
1Q
0B
0I
0W
1R
1'"
0;
0[
0]
0>
0S
b1 f
1n
1G
1J
1\
1L
1X
1`
1_
1^
0o
0m
0j
0}
0|
0y
0p
0k
0$"
0""
0~
0{
0w
0s
0r
0l
b0 5
1+
1*
0("
0*"
b0 8
0,"
1.
1-
#360
0-
#380
1)"
1q
0Z
09
1[
0'"
1H
1;
0\
b10 f
0n
0`
1o
1m
1j
13
11
0.
b1 8
1("
0*
b1 5
0+
1-
#400
0-
#420
00
0e
19
0=
1B
0I
1O
1'"
0H
0;
1>
b11 f
1n
0G
0J
0P
1`
0_
0o
0m
0j
1}
1|
1y
1p
1k
b10 5
0("
b10 8
1*"
1.
03
01
1-
#440
0-
#460
1+"
1t
0)"
0q
0Y
09
0'"
1]
1H
1;
b100 f
0n
0`
1o
1m
1j
0.
b11 8
1("
b11 5
1-
#480
0-
#500
0/
10
0I
1+"
0)"
1t
1N
0e
19
1Z
0q
1=
0?
0B
0O
0K
0W
0R
1'"
0H
0;
0[
0]
0>
1S
b101 f
1n
1G
1J
1P
1\
0L
1X
1`
1_
0^
0o
0m
0j
0}
0|
0y
0p
0k
1$"
1""
1~
1{
1w
1s
1r
1l
b100 5
0("
0*"
b100 8
1,"
1.
1-
#520
0-
#540
1)"
1q
0Z
09
1[
0'"
1H
1;
0\
b110 f
0n
0`
1o
1m
1j
0.
b101 8
1("
b101 5
1-
#560
0-
#580
00
0<
1e
09
1B
0I
1O
1'"
0H
1;
1>
b111 f
1n
0G
0J
0P
1`
0_
0o
0m
0j
1}
1|
1y
1p
1k
b110 5
0("
b110 8
1*"
1.
1-
#600
0-
#620
0+"
0t
1W
0)"
0q
0X
0e
0'"
1]
1H
b0 f
0n
0`
1o
1m
1j
0.
b111 8
1("
1*
b111 5
1+
1-
#640
0-
#660
b11 6
1x
b11 ,
b11 2
b11 4
b11 7
1/
10
19
0;
0+"
1<
0)"
0t
0N
0e
1Z
0q
1Y
1?
0B
0O
0W
1R
1'"
0H
0[
0]
0>
0S
b1 f
1n
1G
1J
1P
1\
1L
1X
1`
1_
1^
0o
0m
0j
0}
0|
0y
0p
0k
0$"
0""
0~
0{
0w
0s
0r
0l
b0 5
0+
0*
0("
0*"
b0 8
0,"
1.
13
11
1-
#680
0-
#700
1)"
1q
0Z
09
1[
0'"
1H
1;
0\
b10 f
0n
0`
1o
1m
1j
03
01
0.
b1 8
1("
b1 5
1-
#720
0-
#740
00
0e
19
0=
1B
0I
1O
1'"
0H
0;
1>
b11 f
1n
0G
0J
0P
1`
0_
0o
0m
0j
1}
1|
1y
1p
1k
b10 5
0("
b10 8
1*"
1.
1-
#760
0-
#780
1+"
1t
0)"
0q
0Y
09
0'"
1]
1H
1;
b100 f
0n
0`
1o
1m
1j
0.
b11 8
1("
b11 5
1-
#800
0-
#820
0/
10
0I
1+"
0)"
1t
1N
0e
19
1Z
0q
1=
0Q
0?
0B
0O
0K
0W
0R
1'"
0H
0;
0[
0]
0>
1S
b101 f
1n
1G
1J
1P
1\
0L
1X
1`
1_
0^
0o
0m
0j
0}
0|
0y
0p
0k
1$"
1""
1~
1{
1w
1s
1r
1l
b100 5
0("
0*"
b100 8
1,"
1.
1-
#840
0-
#860
1)"
1q
0Z
09
1[
0'"
1H
1;
0\
b110 f
0n
0`
1o
1m
1j
0.
b101 8
1("
b101 5
1-
#880
0-
#900
00
0<
1e
09
1B
1I
1'"
0H
1;
1>
b111 f
1n
0G
0J
1`
0_
0o
0m
0j
1}
1|
1y
1p
1k
b110 5
0("
b110 8
1*"
1.
1-
#920
0-
#940
0+"
0t
1W
0)"
0q
0X
0'"
1]
b0 f
0n
0`
1o
1m
1j
0.
b111 8
1("
1*
b111 5
1+
1-
#960
0-
#980
b100 6
0x
1z
0%"
b100 ,
b100 2
b100 4
b100 7
1/
10
0e
19
0;
0+"
1<
0)"
0t
0N
1Z
0q
1Y
1Q
1?
0B
0I
0W
1R
1'"
0[
0]
0>
0S
b1 f
1n
1G
1J
1\
1L
1X
1`
1_
1^
0o
0m
0j
0}
0|
0y
0p
0k
0$"
0""
0~
0{
0w
0s
0r
0l
b0 5
0("
0*"
b0 8
0,"
1.
13
11
1-
#1000
0-
#1020
1)"
1q
0Z
09
1[
0'"
1H
1;
0\
b10 f
0n
0`
1o
1m
1j
0.
b1 8
1("
0*
b1 5
0+
1-
#1040
0-
#1060
00
0e
19
0=
1B
0I
1O
1'"
0H
0;
1>
b11 f
1n
0G
0J
0P
1`
0_
0o
0m
0j
1}
1|
1y
1p
1k
b10 5
0("
b10 8
1*"
1.
03
01
1-
#1080
0-
#1100
1+"
1t
0)"
0q
0Y
09
0'"
1]
1H
1;
b100 f
0n
0`
1o
1m
1j
0.
b11 8
1("
b11 5
1-
#1120
0-
#1140
0/
10
1I
1+"
0)"
1t
0e
19
1Z
0q
1=
0B
0O
1K
0W
0R
1'"
0H
0;
0[
0]
0>
1S
b101 f
1n
1G
0J
1P
1\
0L
1X
1`
1_
0^
0o
0m
0j
0}
0|
0y
0p
0k
1$"
1""
1~
1{
1w
1s
1r
1l
b100 5
0("
0*"
b100 8
1,"
1.
1-
#1160
0-
#1180
1)"
1q
1e
0Z
09
1[
0'"
1;
0\
b110 f
0n
0`
1o
1m
1j
0.
b101 8
1("
b101 5
1-
#1200
0-
#1220
00
0e
0I
19
0=
1B
1O
1'"
0;
1>
b111 f
1n
0G
0P
1`
0_
0o
0m
0j
1}
1|
1y
1p
1k
b110 5
1+
1*
0("
b110 8
1*"
1.
1-
#1240
0-
#1260
0+"
0t
1W
0)"
0q
0X
09
0'"
1]
1H
1;
b0 f
0n
0`
1o
1m
1j
13
11
0.
b111 8
1("
0*
b111 5
0+
1-
#1280
0-
#1300
b101 6
1x
b101 ,
b101 2
b101 4
b101 7
1/
10
0+"
0I
0)"
1J
0t
0e
19
1Z
0q
1Y
1=
0B
0O
0K
0W
1R
1'"
0H
0;
0[
0]
0>
0S
b1 f
1n
1G
1P
1\
1L
1X
1`
1_
1^
0o
0m
0j
0}
0|
0y
0p
0k
0$"
0""
0~
0{
0w
0s
0r
0l
b0 5
0("
0*"
b0 8
0,"
1.
03
01
1-
#1320
0-
#1340
1)"
1q
0Z
09
1[
0'"
1H
1;
0\
b10 f
0n
0`
1o
1m
1j
0.
b1 8
1("
b1 5
1-
#1360
0-
#1380
00
0e
19
0=
1B
0I
1O
1'"
0H
0;
1>
b11 f
1n
0G
0J
0P
1`
0_
0o
0m
0j
1}
1|
1y
1p
1k
b10 5
0("
b10 8
1*"
1.
1-
#1400
0-
#1420
1+"
1t
0)"
0q
0Y
09
0'"
1]
1H
1;
b100 f
0n
0`
1o
1m
1j
0.
b11 8
1("
b11 5
1-
#1440
0-
#1460
0/
10
1I
1+"
0)"
1t
0e
19
1Z
0q
1=
0Q
0B
0O
1K
0W
0R
1'"
0H
0;
0[
0]
0>
1S
b101 f
1n
1G
0J
1P
1\
0L
1X
1`
1_
0^
0o
0m
0j
0}
0|
0y
0p
0k
1$"
1""
1~
1{
1w
1s
1r
1l
b100 5
0("
0*"
b100 8
1,"
1.
1-
#1480
0-
#1500
1)"
1q
1e
0Z
09
1[
0'"
1;
0\
b110 f
0n
0`
1o
1m
1j
0.
b101 8
1("
b101 5
1-
#1520
0-
#1540
00
0e
19
0=
1B
1'"
0;
1>
b111 f
1n
0G
1`
0_
0o
0m
0j
1}
1|
1y
1p
1k
b110 5
1+
1*
0("
b110 8
1*"
1.
1-
#1560
0-
#1580
0+"
0t
1W
1e
0)"
0q
0X
09
0'"
1]
1;
b0 f
0n
0`
1o
1m
1j
13
11
0.
b111 8
1("
0*
b111 5
0+
1-
#1600
0-
#1620
b110 6
0x
1%"
b110 ,
b110 2
b110 4
b110 7
1/
10
0I
0e
0+"
0)"
1J
0t
19
1Z
0q
1Y
1=
1Q
0B
0K
0W
1R
1'"
0;
0[
0]
0>
0S
b1 f
1n
1G
1\
1L
1X
1`
1_
1^
0o
0m
0j
0}
0|
0y
0p
0k
0$"
0""
0~
0{
0w
0s
0r
0l
b0 5
1+
1*
0("
0*"
b0 8
0,"
1.
03
01
1-
#1640
0-
#1660
1)"
1q
0Z
09
1[
0'"
1H
1;
0\
b10 f
0n
0`
1o
1m
1j
13
11
0.
b1 8
1("
0*
b1 5
0+
1-
#1680
0-
#1700
00
0e
19
0=
1B
0I
1O
1'"
0H
0;
1>
b11 f
1n
0G
0J
0P
1`
0_
0o
0m
0j
1}
1|
1y
1p
1k
b10 5
0("
b10 8
1*"
1.
03
01
1-
#1720
0-
#1740
1+"
1t
0)"
0q
0Y
09
0'"
1]
1H
1;
b100 f
0n
0`
1o
1m
1j
0.
b11 8
1("
b11 5
1-
#1760
0-
