partoserial/probador.v
module probador(
    input data_out_conduc,
    input data_out_estruct,
    output reg[7:0]data_in,
    output reg valid_in,
    output reg reset,
    output reg clk_8f);

    reg clk_f;
    reg clk_4f;
    reg clk_ff;
    reg cond;
    reg estruct;
   initial begin
    $dumpfile("bancopruebas.vcd");
    $dumpvars;
    $display("\t\ttime,\t reset, clk_f, clk_8f, valid_in, data_in, data_out_cond, data_out_estruct");

    $monitor($time,"\t%b,\t%b,\t%b,\t%b,\t%h,\t%b,\t%b",reset, clk_f, clk_8f, valid_in, data_in, data_out_conduc, data_out_estruct);
    reset<='b0;
    data_in<='b0;
    valid_in<='b0;
    
    @(posedge clk_f);
	reset<='b1;
    valid_in<='b1;
	data_in<=data_in+1;
    
    repeat (10) begin
    @(posedge clk_f);
    data_in<=data_in+1;
    end

    @(posedge clk_f);
    valid_in<='b0;
    data_in<=data_in+1;

    repeat (2) begin
    @(posedge clk_f);
    data_in<=data_in+1;
    end
     
    $finish;
      
   end

    initial begin
    clk_8f <=0;
    clk_4f <=0;
    clk_f <=0;  
    clk_ff<=0;  
    
    end
    always #2 clk_8f <=~clk_8f;
    
    always @(posedge clk_8f)begin
        clk_4f<=~clk_4f;
    end

    always @(posedge clk_4f)begin
        clk_ff<=~clk_ff;
    end

    always @(posedge clk_ff)begin
        clk_f<=~clk_f;
    end
    
   always @(posedge clk_8f) begin
      cond<=data_out_conduc;
      estruct<=data_out_estruct;
      if (reset) begin
      if(cond==estruct)
         $display("Las descripciones son iguales en ambas salidas");   
      end 
   end

endmodule

partoserial/partoserialSynth.v
/* Generated by Yosys 0.8 (git sha1 UNKNOWN, clang 6.0.0-1ubuntu2 -fPIC -Os) */
`include "./CMOS/cmos_cells.v"

module partoserialSynth(data_in, valid_in, reset, clk_8f, data_out);
  wire [3:0] _000_;
  wire _001_;
  wire [7:0] _002_;
  wire _003_;
  wire _004_;
  wire _005_;
  wire _006_;
  wire _007_;
  wire _008_;
  wire _009_;
  wire _010_;
  wire _011_;
  wire _012_;
  wire _013_;
  wire _014_;
  wire _015_;
  wire _016_;
  wire _017_;
  wire _018_;
  wire _019_;
  wire _020_;
  wire _021_;
  wire _022_;
  wire _023_;
  wire _024_;
  wire _025_;
  wire _026_;
  wire _027_;
  wire _028_;
  wire _029_;
  wire _030_;
  wire _031_;
  wire _032_;
  wire _033_;
  wire _034_;
  wire _035_;
  wire _036_;
  wire _037_;
  wire _038_;
  wire _039_;
  wire _040_;
  wire _041_;
  wire _042_;
  wire _043_;
  wire _044_;
  wire _045_;
  wire _046_;
  wire _047_;
  wire _048_;
  wire _049_;
  wire _050_;
  wire _051_;
  wire _052_;
  wire _053_;
  wire _054_;
  wire _055_;
  wire _056_;
  wire _057_;
  input clk_8f;
  wire [3:0] contador;
  wire [7:0] data2send;
  input [7:0] data_in;
  output data_out;
  input reset;
  input valid_in;
  NOT _058_ (
    .A(contador[3]),
    .Y(_014_)
  );
  NOT _059_ (
    .A(reset),
    .Y(_015_)
  );
  NOT _060_ (
    .A(data_in[0]),
    .Y(_016_)
  );
  NOT _061_ (
    .A(data_in[1]),
    .Y(_017_)
  );
  NOT _062_ (
    .A(data_in[2]),
    .Y(_018_)
  );
  NOT _063_ (
    .A(data_in[3]),
    .Y(_019_)
  );
  NOT _064_ (
    .A(data_in[4]),
    .Y(_020_)
  );
  NOT _065_ (
    .A(data_in[5]),
    .Y(_021_)
  );
  NOT _066_ (
    .A(data_in[6]),
    .Y(_022_)
  );
  NOT _067_ (
    .A(data_in[7]),
    .Y(_023_)
  );
  NOT _068_ (
    .A(valid_in),
    .Y(_024_)
  );
  NOT _069_ (
    .A(contador[0]),
    .Y(_025_)
  );
  NOT _070_ (
    .A(contador[1]),
    .Y(_026_)
  );
  NOT _071_ (
    .A(contador[2]),
    .Y(_027_)
  );
  NOR _072_ (
    .A(_015_),
    .B(contador[0]),
    .Y(_000_[0])
  );
  NOR _073_ (
    .A(_025_),
    .B(_026_),
    .Y(_028_)
  );
  NAND _074_ (
    .A(contador[0]),
    .B(contador[1]),
    .Y(_029_)
  );
  NOR _075_ (
    .A(contador[0]),
    .B(contador[1]),
    .Y(_030_)
  );
  NOT _076_ (
    .A(_030_),
    .Y(_031_)
  );
  NAND _077_ (
    .A(reset),
    .B(_031_),
    .Y(_032_)
  );
  NOR _078_ (
    .A(_028_),
    .B(_032_),
    .Y(_000_[1])
  );
  NOR _079_ (
    .A(contador[2]),
    .B(_028_),
    .Y(_033_)
  );
  NAND _080_ (
    .A(contador[2]),
    .B(_028_),
    .Y(_034_)
  );
  NAND _081_ (
    .A(reset),
    .B(_034_),
    .Y(_035_)
  );
  NOR _082_ (
    .A(_033_),
    .B(_035_),
    .Y(_000_[2])
  );
  NOR _083_ (
    .A(_014_),
    .B(_035_),
    .Y(_000_[3])
  );
  NAND _084_ (
    .A(reset),
    .B(valid_in),
    .Y(_036_)
  );
  NOR _085_ (
    .A(_016_),
    .B(_036_),
    .Y(data2send[0])
  );
  NAND _086_ (
    .A(reset),
    .B(_024_),
    .Y(_037_)
  );
  NAND _087_ (
    .A(data_in[0]),
    .B(_037_),
    .Y(_038_)
  );
  NOT _088_ (
    .A(_038_),
    .Y(_002_[0])
  );
  NOR _089_ (
    .A(_017_),
    .B(_036_),
    .Y(data2send[1])
  );
  NAND _090_ (
    .A(data_in[1]),
    .B(_037_),
    .Y(_039_)
  );
  NOT _091_ (
    .A(_039_),
    .Y(_002_[1])
  );
  NOR _092_ (
    .A(data_in[2]),
    .B(_036_),
    .Y(_040_)
  );
  NOT _093_ (
    .A(_040_),
    .Y(data2send[2])
  );
  NAND _094_ (
    .A(_018_),
    .B(_037_),
    .Y(_002_[2])
  );
  NOR _095_ (
    .A(data_in[3]),
    .B(_036_),
    .Y(_041_)
  );
  NOT _096_ (
    .A(_041_),
    .Y(data2send[3])
  );
  NAND _097_ (
    .A(_019_),
    .B(_037_),
    .Y(_002_[3])
  );
  NOR _098_ (
    .A(data_in[4]),
    .B(_036_),
    .Y(_042_)
  );
  NOT _099_ (
    .A(_042_),
    .Y(data2send[4])
  );
  NAND _100_ (
    .A(_020_),
    .B(_037_),
    .Y(_002_[4])
  );
  NOR _101_ (
    .A(data_in[5]),
    .B(_036_),
    .Y(_043_)
  );
  NOT _102_ (
    .A(_043_),
    .Y(data2send[5])
  );
  NAND _103_ (
    .A(_021_),
    .B(_037_),
    .Y(_002_[5])
  );
  NOR _104_ (
    .A(_022_),
    .B(_036_),
    .Y(data2send[6])
  );
  NAND _105_ (
    .A(data_in[6]),
    .B(_037_),
    .Y(_044_)
  );
  NOT _106_ (
    .A(_044_),
    .Y(_002_[6])
  );
  NOR _107_ (
    .A(data_in[7]),
    .B(_036_),
    .Y(_045_)
  );
  NOT _108_ (
    .A(_045_),
    .Y(data2send[7])
  );
  NAND _109_ (
    .A(_023_),
    .B(_037_),
    .Y(_002_[7])
  );
  NOR _110_ (
    .A(_027_),
    .B(_041_),
    .Y(_046_)
  );
  NOR _111_ (
    .A(contador[2]),
    .B(_045_),
    .Y(_047_)
  );
  NOR _112_ (
    .A(_046_),
    .B(_047_),
    .Y(_048_)
  );
  NAND _113_ (
    .A(_030_),
    .B(_048_),
    .Y(_049_)
  );
  NOR _114_ (
    .A(_027_),
    .B(_040_),
    .Y(_050_)
  );
  NAND _115_ (
    .A(contador[0]),
    .B(_026_),
    .Y(_051_)
  );
  NAND _116_ (
    .A(_027_),
    .B(data2send[6]),
    .Y(_052_)
  );
  NOR _117_ (
    .A(_050_),
    .B(_051_),
    .Y(_053_)
  );
  NAND _118_ (
    .A(_052_),
    .B(_053_),
    .Y(_054_)
  );
  NAND _119_ (
    .A(_049_),
    .B(_054_),
    .Y(_055_)
  );
  NOR _120_ (
    .A(contador[2]),
    .B(_043_),
    .Y(_056_)
  );
  NAND _121_ (
    .A(contador[2]),
    .B(data2send[1]),
    .Y(_057_)
  );
  NAND _122_ (
    .A(contador[1]),
    .B(_057_),
    .Y(_003_)
  );
  NOT _123_ (
    .A(_003_),
    .Y(_004_)
  );
  NOR _124_ (
    .A(contador[0]),
    .B(_056_),
    .Y(_005_)
  );
  NAND _125_ (
    .A(_004_),
    .B(_005_),
    .Y(_006_)
  );
  NOR _126_ (
    .A(_034_),
    .B(data2send[0]),
    .Y(_007_)
  );
  NOR _127_ (
    .A(contador[3]),
    .B(_015_),
    .Y(_008_)
  );
  NOR _128_ (
    .A(contador[2]),
    .B(_029_),
    .Y(_009_)
  );
  NAND _129_ (
    .A(_042_),
    .B(_009_),
    .Y(_010_)
  );
  NAND _130_ (
    .A(_008_),
    .B(_010_),
    .Y(_011_)
  );
  NOR _131_ (
    .A(_007_),
    .B(_011_),
    .Y(_012_)
  );
  NAND _132_ (
    .A(_006_),
    .B(_012_),
    .Y(_013_)
  );
  NOR _133_ (
    .A(_055_),
    .B(_013_),
    .Y(_001_)
  );
  DFF _134_ (
    .C(clk_8f),
    .D(_001_),
    .Q(data_out)
  );
  DFF _135_ (
    .C(clk_8f),
    .D(_002_[0]),
    .Q(data2send[0])
  );
  DFF _136_ (
    .C(clk_8f),
    .D(_002_[1]),
    .Q(data2send[1])
  );
  DFF _137_ (
    .C(clk_8f),
    .D(_002_[2]),
    .Q(data2send[2])
  );
  DFF _138_ (
    .C(clk_8f),
    .D(_002_[3]),
    .Q(data2send[3])
  );
  DFF _139_ (
    .C(clk_8f),
    .D(_002_[4]),
    .Q(data2send[4])
  );
  DFF _140_ (
    .C(clk_8f),
    .D(_002_[5]),
    .Q(data2send[5])
  );
  DFF _141_ (
    .C(clk_8f),
    .D(_002_[6]),
    .Q(data2send[6])
  );
  DFF _142_ (
    .C(clk_8f),
    .D(_002_[7]),
    .Q(data2send[7])
  );
  DFF _143_ (
    .C(clk_8f),
    .D(_000_[0]),
    .Q(contador[0])
  );
  DFF _144_ (
    .C(clk_8f),
    .D(_000_[1]),
    .Q(contador[1])
  );
  DFF _145_ (
    .C(clk_8f),
    .D(_000_[2]),
    .Q(contador[2])
  );
  DFF _146_ (
    .C(clk_8f),
    .D(_000_[3]),
    .Q(contador[3])
  );
endmodule

partoserial/partoserial.v
module partoserial(
    input [7:0]data_in,
    input valid_in,
    input reset,
    input clk_8f,
    output reg data_out);

reg [7:0]data2send;
reg [3:0]contador;

always @(*)begin
//data_out=data2send[7-contador];
    if(reset==0)begin
        data2send='hBC;
    end
    else begin
       if (valid_in==1)
            data2send=data_in;
        else
            data2send='hBC; 
    end
 
end


always @(posedge clk_8f)begin
    if(reset==0)begin
        data_out<='b0;
        //data2send<=data_in;
        contador<=0;
    end
    else begin    
        data_out<=data2send[7-contador];
        contador<=contador+1;
        if(contador==7)begin
            contador<='b0;
        end
    end
end

endmodule

partoserial/bancopruebas.v
`timescale 1ns /100 ps

`include "probador.v"
`include "partoserial.v"
`include "partoserialSynth.v"

module bancopruebas;
    wire[7:0] data_in;
    wire clk_f,clk_8f,reset,valid_in,data_out_conduc,data_out_estruct;
    
    
	partoserial modul_cond(/*AUTOINST*/
			       // Outputs
			       .data_out	(data_out_conduc),
			       // Inputs
			       .data_in		(data_in[7:0]),
			       .valid_in	(valid_in),
			       .reset		(reset),
			       .clk_8f		(clk_8f)); 
	partoserialSynth modul_estruct(/*AUTOINST*/
				       // Outputs
				       .data_out	(data_out_estruct),
				       // Inputs
				       .clk_8f		(clk_8f),
				       .data_in		(data_in[7:0]),
				       .reset		(reset),
				       .valid_in	(valid_in));  
	probador mi_probador(/*AUTOINST*/
			     // Outputs
			     .data_in		(data_in[7:0]),
			     .valid_in		(valid_in),
			     .reset		(reset),
			     .clk_8f		(clk_8f),
			     // Inputs
			     .data_out_conduc	(data_out_conduc),
			     .data_out_estruct	(data_out_estruct));
endmodule

byte_stripping/cmos_cells.v
module BUF(input A,output Y);
assign Y = A;
endmodule

module NOT(input A,output Y);
assign Y = ~A;
endmodule

module NAND(input A, input B, output Y);
assign Y = ~(A & B);
endmodule

module NOR(input A, input B, output Y);
assign Y = ~(A | B);
endmodule

module DFF(input C, input D, output reg Q);
always @(posedge C)
	Q <= D;
endmodule

module DFFSR(input C, input D, input S, input R, output reg Q);
always @(posedge C, posedge S, posedge R)
	if (S)
		Q <= 1'b1;
	else if (R)
		Q <= 1'b0;
	else
		Q <= D;
endmodule

partoserial/bancopruebas.vcd
$date
	Wed May 15 16:46:38 2019
$end
$version
	Icarus Verilog
$end
$timescale
	100ps
$end
$scope module BUF $end
$var wire 1 ! A $end
$var wire 1 " Y $end
$upscope $end
$scope module DFFSR $end
$var wire 1 # C $end
$var wire 1 $ D $end
$var wire 1 % R $end
$var wire 1 & S $end
$var reg 1 ' Q $end
$upscope $end
$scope module bancopruebas $end
$var wire 1 ( valid_in $end
$var wire 1 ) reset $end
$var wire 1 * data_out_estruct $end
$var wire 1 + data_out_conduc $end
$var wire 8 , data_in [7:0] $end
$var wire 1 - clk_8f $end
$scope module mi_probador $end
$var wire 1 * data_out_estruct $end
$var wire 1 + data_out_conduc $end
$var reg 1 . clk_4f $end
$var reg 1 - clk_8f $end
$var reg 1 / clk_f $end
$var reg 1 0 clk_ff $end
$var reg 1 1 cond $end
$var reg 8 2 data_in [7:0] $end
$var reg 1 3 estruct $end
$var reg 1 ) reset $end
$var reg 1 ( valid_in $end
$upscope $end
$scope module modul_cond $end
$var wire 1 - clk_8f $end
$var wire 8 4 data_in [7:0] $end
$var wire 1 ) reset $end
$var wire 1 ( valid_in $end
$var reg 4 5 contador [3:0] $end
$var reg 8 6 data2send [7:0] $end
$var reg 1 + data_out $end
$upscope $end
$scope module modul_estruct $end
$var wire 1 - clk_8f $end
$var wire 8 7 data2send [7:0] $end
$var wire 8 8 data_in [7:0] $end
$var wire 1 ) reset $end
$var wire 1 ( valid_in $end
$var wire 1 * data_out $end
$var wire 4 9 contador [3:0] $end
$var wire 1 : _057_ $end
$var wire 1 ; _056_ $end
$var wire 1 < _055_ $end
$var wire 1 = _054_ $end
$var wire 1 > _053_ $end
$var wire 1 ? _052_ $end
$var wire 1 @ _051_ $end
$var wire 1 A _050_ $end
$var wire 1 B _049_ $end
$var wire 1 C _048_ $end
$var wire 1 D _047_ $end
$var wire 1 E _046_ $end
$var wire 1 F _045_ $end
$var wire 1 G _044_ $end
$var wire 1 H _043_ $end
$var wire 1 I _042_ $end
$var wire 1 J _041_ $end
$var wire 1 K _040_ $end
$var wire 1 L _039_ $end
$var wire 1 M _038_ $end
$var wire 1 N _037_ $end
$var wire 1 O _036_ $end
$var wire 1 P _035_ $end
$var wire 1 Q _034_ $end
$var wire 1 R _033_ $end
$var wire 1 S _032_ $end
$var wire 1 T _031_ $end
$var wire 1 U _030_ $end
$var wire 1 V _029_ $end
$var wire 1 W _028_ $end
$var wire 1 X _027_ $end
$var wire 1 Y _026_ $end
$var wire 1 Z _025_ $end
$var wire 1 [ _024_ $end
$var wire 1 \ _023_ $end
$var wire 1 ] _022_ $end
$var wire 1 ^ _021_ $end
$var wire 1 _ _020_ $end
$var wire 1 ` _019_ $end
$var wire 1 a _018_ $end
$var wire 1 b _017_ $end
$var wire 1 c _016_ $end
$var wire 1 d _015_ $end
$var wire 1 e _014_ $end
$var wire 1 f _013_ $end
$var wire 1 g _012_ $end
$var wire 1 h _011_ $end
$var wire 1 i _010_ $end
$var wire 1 j _009_ $end
$var wire 1 k _008_ $end
$var wire 1 l _007_ $end
$var wire 1 m _006_ $end
$var wire 1 n _005_ $end
$var wire 1 o _004_ $end
$var wire 1 p _003_ $end
$var wire 8 q _002_ [7:0] $end
$var wire 1 r _001_ $end
$var wire 4 s _000_ [3:0] $end
$scope module _058_ $end
$var wire 1 t A $end
$var wire 1 e Y $end
$upscope $end
$scope module _059_ $end
$var wire 1 ) A $end
$var wire 1 d Y $end
$upscope $end
$scope module _060_ $end
$var wire 1 u A $end
$var wire 1 c Y $end
$upscope $end
$scope module _061_ $end
$var wire 1 v A $end
$var wire 1 b Y $end
$upscope $end
$scope module _062_ $end
$var wire 1 w A $end
$var wire 1 a Y $end
$upscope $end
$scope module _063_ $end
$var wire 1 x A $end
$var wire 1 ` Y $end
$upscope $end
$scope module _064_ $end
$var wire 1 y A $end
$var wire 1 _ Y $end
$upscope $end
$scope module _065_ $end
$var wire 1 z A $end
$var wire 1 ^ Y $end
$upscope $end
$scope module _066_ $end
$var wire 1 { A $end
$var wire 1 ] Y $end
$upscope $end
$scope module _067_ $end
$var wire 1 | A $end
$var wire 1 \ Y $end
$upscope $end
$scope module _068_ $end
$var wire 1 ( A $end
$var wire 1 [ Y $end
$upscope $end
$scope module _069_ $end
$var wire 1 } A $end
$var wire 1 Z Y $end
$upscope $end
$scope module _070_ $end
$var wire 1 ~ A $end
$var wire 1 Y Y $end
$upscope $end
$scope module _071_ $end
$var wire 1 !" A $end
$var wire 1 X Y $end
$upscope $end
$scope module _072_ $end
$var wire 1 d A $end
$var wire 1 "" B $end
$var wire 1 #" Y $end
$upscope $end
$scope module _073_ $end
$var wire 1 Z A $end
$var wire 1 Y B $end
$var wire 1 W Y $end
$upscope $end
$scope module _074_ $end
$var wire 1 $" A $end
$var wire 1 %" B $end
$var wire 1 V Y $end
$upscope $end
$scope module _075_ $end
$var wire 1 &" A $end
$var wire 1 '" B $end
$var wire 1 U Y $end
$upscope $end
$scope module _076_ $end
$var wire 1 U A $end
$var wire 1 T Y $end
$upscope $end
$scope module _077_ $end
$var wire 1 ) A $end
$var wire 1 T B $end
$var wire 1 S Y $end
$upscope $end
$scope module _078_ $end
$var wire 1 W A $end
$var wire 1 S B $end
$var wire 1 (" Y $end
$upscope $end
$scope module _079_ $end
$var wire 1 )" A $end
$var wire 1 W B $end
$var wire 1 R Y $end
$upscope $end
$scope module _080_ $end
$var wire 1 *" A $end
$var wire 1 W B $end
$var wire 1 Q Y $end
$upscope $end
$scope module _081_ $end
$var wire 1 ) A $end
$var wire 1 Q B $end
$var wire 1 P Y $end
$upscope $end
$scope module _082_ $end
$var wire 1 R A $end
$var wire 1 P B $end
$var wire 1 +" Y $end
$upscope $end
$scope module _083_ $end
$var wire 1 e A $end
$var wire 1 P B $end
$var wire 1 ," Y $end
$upscope $end
$scope module _084_ $end
$var wire 1 ) A $end
$var wire 1 ( B $end
$var wire 1 O Y $end
$upscope $end
$scope module _085_ $end
$var wire 1 c A $end
$var wire 1 O B $end
$var wire 1 -" Y $end
$upscope $end
$scope module _086_ $end
$var wire 1 ) A $end
$var wire 1 [ B $end
$var wire 1 N Y $end
$upscope $end
$scope module _087_ $end
$var wire 1 ." A $end
$var wire 1 N B $end
$var wire 1 M Y $end
$upscope $end
$scope module _088_ $end
$var wire 1 M A $end
$var wire 1 /" Y $end
$upscope $end
$scope module _089_ $end
$var wire 1 b A $end
$var wire 1 O B $end
$var wire 1 0" Y $end
$upscope $end
$scope module _090_ $end
$var wire 1 1" A $end
$var wire 1 N B $end
$var wire 1 L Y $end
$upscope $end
$scope module _091_ $end
$var wire 1 L A $end
$var wire 1 2" Y $end
$upscope $end
$scope module _092_ $end
$var wire 1 3" A $end
$var wire 1 O B $end
$var wire 1 K Y $end
$upscope $end
$scope module _093_ $end
$var wire 1 K A $end
$var wire 1 4" Y $end
$upscope $end
$scope module _094_ $end
$var wire 1 a A $end
$var wire 1 N B $end
$var wire 1 5" Y $end
$upscope $end
$scope module _095_ $end
$var wire 1 6" A $end
$var wire 1 O B $end
$var wire 1 J Y $end
$upscope $end
$scope module _096_ $end
$var wire 1 J A $end
$var wire 1 7" Y $end
$upscope $end
$scope module _097_ $end
$var wire 1 ` A $end
$var wire 1 N B $end
$var wire 1 8" Y $end
$upscope $end
$scope module _098_ $end
$var wire 1 9" A $end
$var wire 1 O B $end
$var wire 1 I Y $end
$upscope $end
$scope module _099_ $end
$var wire 1 I A $end
$var wire 1 :" Y $end
$upscope $end
$scope module _100_ $end
$var wire 1 _ A $end
$var wire 1 N B $end
$var wire 1 ;" Y $end
$upscope $end
$scope module _101_ $end
$var wire 1 <" A $end
$var wire 1 O B $end
$var wire 1 H Y $end
$upscope $end
$scope module _102_ $end
$var wire 1 H A $end
$var wire 1 =" Y $end
$upscope $end
$scope module _103_ $end
$var wire 1 ^ A $end
$var wire 1 N B $end
$var wire 1 >" Y $end
$upscope $end
$scope module _104_ $end
$var wire 1 ] A $end
$var wire 1 O B $end
$var wire 1 ?" Y $end
$upscope $end
$scope module _105_ $end
$var wire 1 @" A $end
$var wire 1 N B $end
$var wire 1 G Y $end
$upscope $end
$scope module _106_ $end
$var wire 1 G A $end
$var wire 1 A" Y $end
$upscope $end
$scope module _107_ $end
$var wire 1 B" A $end
$var wire 1 O B $end
$var wire 1 F Y $end
$upscope $end
$scope module _108_ $end
$var wire 1 F A $end
$var wire 1 C" Y $end
$upscope $end
$scope module _109_ $end
$var wire 1 \ A $end
$var wire 1 N B $end
$var wire 1 D" Y $end
$upscope $end
$scope module _110_ $end
$var wire 1 X A $end
$var wire 1 J B $end
$var wire 1 E Y $end
$upscope $end
$scope module _111_ $end
$var wire 1 E" A $end
$var wire 1 F B $end
$var wire 1 D Y $end
$upscope $end
$scope module _112_ $end
$var wire 1 E A $end
$var wire 1 D B $end
$var wire 1 C Y $end
$upscope $end
$scope module _113_ $end
$var wire 1 U A $end
$var wire 1 C B $end
$var wire 1 B Y $end
$upscope $end
$scope module _114_ $end
$var wire 1 X A $end
$var wire 1 K B $end
$var wire 1 A Y $end
$upscope $end
$scope module _115_ $end
$var wire 1 F" A $end
$var wire 1 Y B $end
$var wire 1 @ Y $end
$upscope $end
$scope module _116_ $end
$var wire 1 X A $end
$var wire 1 G" B $end
$var wire 1 ? Y $end
$upscope $end
$scope module _117_ $end
$var wire 1 A A $end
$var wire 1 @ B $end
$var wire 1 > Y $end
$upscope $end
$scope module _118_ $end
$var wire 1 ? A $end
$var wire 1 > B $end
$var wire 1 = Y $end
$upscope $end
$scope module _119_ $end
$var wire 1 B A $end
$var wire 1 = B $end
$var wire 1 < Y $end
$upscope $end
$scope module _120_ $end
$var wire 1 H" A $end
$var wire 1 H B $end
$var wire 1 ; Y $end
$upscope $end
$scope module _121_ $end
$var wire 1 I" A $end
$var wire 1 J" B $end
$var wire 1 : Y $end
$upscope $end
$scope module _122_ $end
$var wire 1 K" A $end
$var wire 1 : B $end
$var wire 1 p Y $end
$upscope $end
$scope module _123_ $end
$var wire 1 p A $end
$var wire 1 o Y $end
$upscope $end
$scope module _124_ $end
$var wire 1 L" A $end
$var wire 1 ; B $end
$var wire 1 n Y $end
$upscope $end
$scope module _125_ $end
$var wire 1 o A $end
$var wire 1 n B $end
$var wire 1 m Y $end
$upscope $end
$scope module _126_ $end
$var wire 1 Q A $end
$var wire 1 M" B $end
$var wire 1 l Y $end
$upscope $end
$scope module _127_ $end
$var wire 1 N" A $end
$var wire 1 d B $end
$var wire 1 k Y $end
$upscope $end
$scope module _128_ $end
$var wire 1 O" A $end
$var wire 1 V B $end
$var wire 1 j Y $end
$upscope $end
$scope module _129_ $end
$var wire 1 I A $end
$var wire 1 j B $end
$var wire 1 i Y $end
$upscope $end
$scope module _130_ $end
$var wire 1 k A $end
$var wire 1 i B $end
$var wire 1 h Y $end
$upscope $end
$scope module _131_ $end
$var wire 1 l A $end
$var wire 1 h B $end
$var wire 1 g Y $end
$upscope $end
$scope module _132_ $end
$var wire 1 m A $end
$var wire 1 g B $end
$var wire 1 f Y $end
$upscope $end
$scope module _133_ $end
$var wire 1 < A $end
$var wire 1 f B $end
$var wire 1 r Y $end
$upscope $end
$scope module _134_ $end
$var wire 1 - C $end
$var wire 1 r D $end
$var reg 1 * Q $end
$upscope $end
$scope module _135_ $end
$var wire 1 - C $end
$var wire 1 P" D $end
$var reg 1 Q" Q $end
$upscope $end
$scope module _136_ $end
$var wire 1 - C $end
$var wire 1 R" D $end
$var reg 1 S" Q $end
$upscope $end
$scope module _137_ $end
$var wire 1 - C $end
$var wire 1 T" D $end
$var reg 1 U" Q $end
$upscope $end
$scope module _138_ $end
$var wire 1 - C $end
$var wire 1 V" D $end
$var reg 1 W" Q $end
$upscope $end
$scope module _139_ $end
$var wire 1 - C $end
$var wire 1 X" D $end
$var reg 1 Y" Q $end
$upscope $end
$scope module _140_ $end
$var wire 1 - C $end
$var wire 1 Z" D $end
$var reg 1 [" Q $end
$upscope $end
$scope module _141_ $end
$var wire 1 - C $end
$var wire 1 \" D $end
$var reg 1 ]" Q $end
$upscope $end
$scope module _142_ $end
$var wire 1 - C $end
$var wire 1 ^" D $end
$var reg 1 _" Q $end
$upscope $end
$scope module _143_ $end
$var wire 1 - C $end
$var wire 1 `" D $end
$var reg 1 a" Q $end
$upscope $end
$scope module _144_ $end
$var wire 1 - C $end
$var wire 1 b" D $end
$var reg 1 c" Q $end
$upscope $end
$scope module _145_ $end
$var wire 1 - C $end
$var wire 1 d" D $end
$var reg 1 e" Q $end
$upscope $end
$scope module _146_ $end
$var wire 1 - C $end
$var wire 1 f" D $end
$var reg 1 g" Q $end
$upscope $end
$upscope $end
$upscope $end
$enddefinitions $end
#0
$dumpvars
xg"
0f"
xe"
0d"
xc"
0b"
xa"
0`"
x_"
0^"
x]"
0\"
x["
0Z"
xY"
0X"
xW"
0V"
xU"
0T"
xS"
0R"
xQ"
0P"
xO"
xN"
xM"
xL"
xK"
xJ"
xI"
xH"
xG"
xF"
xE"
0D"
1C"
0B"
0A"
0@"
0?"
0>"
1="
0<"
0;"
1:"
09"
08"
17"
06"
05"
14"
03"
02"
01"
00"
0/"
0."
0-"
0,"
0+"
x*"
x)"
0("
x'"
x&"
x%"
x$"
0#"
x""
x!"
x~
x}
0|
0{
0z
0y
0x
0w
0v
0u
xt
b0 s
0r
b0 q
xp
xo
xn
xm
xl
0k
xj
1i
1h
0g
1f
xe
1d
1c
1b
1a
1`
1_
1^
1]
1\
1[
xZ
xY
xX
xW
xV
xU
xT
1S
xR
xQ
1P
1O
1N
1M
1L
0K
0J
0I
0H
1G
0F
xE
xD
xC
xB
xA
x@
x?
x>
x=
x<
x;
x:
bx 9
b0 8
bx 7
b10111100 6
bx 5
b0 4
x3
b0 2
x1
00
0/
0.
0-
b0 ,
x+
x*
0)
0(
x'
z&
z%
z$
z#
z"
z!
$end
#20
1P"
1-"
1/"
0M
0c
1u
1."
b1 ,
b1 2
b1 4
b1 8
1/
10
0r
1<
0f
1=
0B
1g
1m
1R
1i
0>
0j
1n
1C
0l
0h
0b"
0d"
04"
07"
0:"
0="
0C"
0T"
0V"
0X"
0Z"
0^"
0o
0T
0W
0E
0A
1`"
0("
0+"
1K
1J
1I
1H
1F
05"
08"
0;"
0>"
b1 q
0D"
1?
1@
1p
1U
1V
1:
0;
0D
1Q
b1 s
1#"
1k
1Z
1Y
1X
1e
1S
0P
0O
1N
xM"
0J"
0G"
0L"
0F"
0&"
0$"
0""
0}
0K"
0'"
0%"
0~
0O"
0I"
0H"
0E"
0*"
0)"
0!"
0N"
0t
0[
0d
b0 5
b1 6
0+
0*
0Q"
0S"
0U"
0W"
0Y"
0["
b0x 7
0]"
0_"
0a"
0c"
0e"
b0 9
0g"
1(
1)
1.
1-
#40
0-
#60
1b"
0r
1("
0=
1<
0S
1>
1B
1T
0`"
0n
0@
0U
b10 s
0#"
0Z
1L"
1F"
1&"
1$"
1""
1}
1M"
03
01
0.
b1 9
1a"
b1 7
1Q"
b1 5
1-
#80
0-
#100
00
0<
1f
1=
0m
0>
1`"
1o
1n
1@
b11 s
1#"
0p
1Z
0Y
0L"
0F"
0&"
0$"
0""
0}
1K"
1'"
1%"
1~
b10 5
0a"
b10 9
1c"
1.
1-
#120
0-
#140
0g
0r
1h
1d"
1+"
1f
0i
0b"
0("
0R
1m
1j
0`"
1W
0n
0V
b100 s
0#"
0Z
1L"
1F"
1&"
1$"
1""
1}
0.
b11 9
1a"
b11 5
1-
#160
0-
#180
0/
10
0f
1g
1d"
1<
0b"
0h
1+"
1S
0("
0B
1i
0P
1`"
0o
0T
0W
1n
b101 s
1#"
1p
1U
1V
0j
1Q
1Z
1Y
0X
0L"
0F"
0&"
0$"
0""
0}
0K"
0'"
0%"
0~
1O"
1I"
1H"
1E"
1*"
1)"
1!"
b100 5
0a"
0c"
b100 9
1e"
1.
1-
#200
0-
#220
1b"
0r
1("
0=
1<
0S
1>
1B
1T
0`"
0n
0@
0U
b110 s
0#"
0Z
1L"
1F"
1&"
1$"
1""
1}
0.
b101 9
1a"
b101 5
1-
#240
0-
#260
00
0<
1f
1=
0m
0>
1`"
1o
1n
1@
b111 s
1#"
0p
1Z
0Y
0L"
0F"
0&"
0$"
0""
0}
1K"
1'"
1%"
1~
b110 5
0a"
b110 9
1c"
1.
1-
#280
0-
#300
0d"
0+"
1r
1P
0f
0b"
0("
0Q
1m
0`"
1W
0n
0V
b0 s
0#"
0Z
1L"
1F"
1&"
1$"
1""
1}
0.
b111 9
1a"
b111 5
1-
#320
0-
#340
xM"
xJ"
0P"
1R"
0-"
b0xx 7
10"
0/"
b10 q
12"
1M
0L
1c
0b
b10 6
0u
1v
0."
11"
b10 ,
b10 2
b10 4
b10 8
1/
10
0f
0r
1g
0d"
1<
0b"
0h
0+"
1S
0("
1R
0B
1i
0P
1`"
0o
0T
0W
1n
b1 s
1#"
1p
1U
1V
0j
1Q
1Z
1Y
1X
0L"
0F"
0&"
0$"
0""
0}
0K"
0'"
0%"
0~
0O"
0I"
0H"
0E"
0*"
0)"
0!"
b0 5
1+
1*
0a"
0c"
b0 9
0e"
1.
1-
#360
0-
#380
1b"
0r
1("
0=
1<
0S
1>
1B
1T
0`"
0n
0@
0U
b10 s
0#"
0Z
1L"
1F"
1&"
1$"
1""
1}
1J"
0M"
13
11
0.
b1 9
1a"
1S"
b10 7
0Q"
0*
b1 5
0+
1-
#400
0-
