serialtopar/checker.v
/*
 *Universidad de Costa Rica - Escuela de Ingenieria Electrica
 *Proyecto #1 - IE-0523 - modulo checker del mux
 *@author Giancarlo Marin H.
 *@date   14/05/2019
 *@brief  Modulo de chequeo entre las señales de dos mux uno conductual y otro estructural
*/

module checker(
	output reg		check_data_out,	// salida de 1 bit que indica que ambos datos de data_out son iguales	
	output reg 		check_valid,	// salida de 1 bit que indica que ambos bits de valido son iguales
	input 			clk,			// señal de clock del modulo	
	input 			reset_L,		// señal de reset_L del modulo
	input [7:0]		data_out_c,		// entrada de datos generada por del modulo conductual
	input [7:0]		data_out_e,		// entrada de datos generada por el modulo estructural
	input 			valid_out_c,	// entrada de bit de valido por el modulo conductual
	input 			valid_out_e	// entrada de bit de valido por el modulo estructural
	);
	// ffs de entrada 
	reg [7:0] 		out_c,out_e; 	
	reg 			valid_c,valid_e;
	
	always @(posedge clk) begin		// ffs para registrar las entradas
		if(reset_L==0) begin
			out_c <= 0;
			out_e <= 0;
			valid_c <= 0;
			valid_e <= 0;
		end else begin
			out_c <= data_out_c;
			out_e <= data_out_e;
			valid_c <= valid_out_c;
			valid_e <= valid_out_e;
		end
	end

	always @(posedge clk) begin		// bloque de comparacion en los flancos de reloj
		if (reset_L==1) begin
			if (out_c == out_e) begin
				check_data_out<=1;
			end
			else begin
				check_data_out<=0;
				$display ($time,"Error diferencia entre modulos");
			end 
			if (valid_c==valid_e) begin
				check_valid<=1;
			end
			else begin
				check_valid<=0;
				$display ($time,"Error diferencia entre modulos");
			end 
		end
		else begin
			check_data_out<=1;
			check_valid<=1;
		end
	end
endmodule // checker

serialtopar/probador.v
/*
 *Universidad de Costa Rica - Escuela de Ingenieria Electrica
 *Proyecto #1 - IE-0523 - modulo probador del serialtopar
 *@author Giancarlo Marin H.
 *@date   20/05/2019
 *@brief  Modulo que genera las señales y monitoriza las salidas del modulo serialtopar conductual y estructural sintetizado
*/

`include "checker.v"

module probador (
	output reg 					clk_f,			// generador del clock
	output reg 					clk_8f,			// generador del clock
	output reg 					reset_L,		// generador de reset
	output reg					data_in,		// generador de la entrada de dato 0
	input [7:0]					data_out_c,		// monitor de salida de datos cond
	input [7:0]					data_out_e,		// monitor de salida de datos estr
	input 						valid_out_c, 	// monitor de salida del bit valido cond
	input 						valid_out_e 	// monitor de salida del bit valido estr
	);
	wire check_data_out, check_valid;	// salidas del checker

	checker c0(/*autoinst*/
			.check_data_out(check_data_out),
			.check_valid(check_valid),
			.clk(clk_f),
			.reset_L(reset_L),
			.data_out_c(data_out_c[7:0]),
			.data_out_e(data_out_e[7:0]),
			.valid_out_c(valid_out_c),
			.valid_out_e(valid_out_e));

	initial begin
		$dumpfile("s2p.vcd");		// archivo "dump"
		$dumpvars;					// dumping de variables
		// Mensajes en consola 
		$display ("\t\tclk\treset_L\tdata_in \tdata_out_c valid_out_c\tdata_out_e valid_out_e\tcheck_data_out check_valid_out");
		$monitor($time,"\t%b\t%b\t%x %b\t%x %b\t%b %b", clk_f, reset_L, data_in, data_out_c, valid_out_c, data_out_e, valid_out_e, check_data_out,check_valid);
		// Pruebas
		data_in <= 0; 					
		// Pruebas #1: Reset bajo. 
		reset_L <= 0;
		// Prueba #2: Reset alto. Valido primer dato
		@(posedge clk_f);
		reset_L <= 1;
		// Prueba #3: Envía BC 4 veces
		repeat(4) begin
			@(posedge clk_8f);
			data_in <= 0;
			@(posedge clk_8f);
			data_in <= 0;
			@(posedge clk_8f);
			data_in <= 1;
			@(posedge clk_8f);
			data_in <= 1;
			@(posedge clk_8f);
			data_in <= 1;
			@(posedge clk_8f);
			data_in <= 1;
			@(posedge clk_8f);
			data_in <= 0;
			@(posedge clk_8f);
			data_in <= 1;
		end
		// Prueba #4: Envía 3 datos validos
		repeat(8) begin // envía FF
			@(posedge clk_8f);
			data_in <= 1;
		end
		// envia EE
		repeat(2) begin
			@(posedge clk_8f);
			data_in <= 0;
			@(posedge clk_8f);
			data_in <= 1;
			@(posedge clk_8f);
			data_in <= 1;
			@(posedge clk_8f);
			data_in <= 1;
		end
		//envia DD
		repeat(2) begin
			@(posedge clk_8f);
			data_in <= 1;
			@(posedge clk_8f);
			data_in <= 0;
			@(posedge clk_8f);
			data_in <= 1;
			@(posedge clk_8f);
			data_in <= 1;
		end
		// Prueba #5: Envía BC de nuevo. Se espera valid_out = 0
		@(posedge clk_8f);
		data_in <= 0;
		@(posedge clk_8f);
		data_in <= 0;
		@(posedge clk_8f);
		data_in <= 1;
		@(posedge clk_8f);
		data_in <= 1;
		@(posedge clk_8f);
		data_in <= 1;
		@(posedge clk_8f);
		data_in <= 1;
		@(posedge clk_8f);
		data_in <= 0;
		@(posedge clk_8f);
		data_in <= 1;
		// Prueba 6: Vuelve a enviar otro dato valido
		// envia AA
		repeat(4) begin
			@(posedge clk_8f);
			data_in <= 0;
			@(posedge clk_8f);
			data_in <= 1;
		end
		// Prueba 7: Reset alto y termina de almacenar señales
		repeat(7) begin
			@(posedge clk_8f);
		end
		reset_L <= 0;
		@(posedge clk_f);
		$finish;	
	end
	// Generador del clk
	initial	begin
		clk_f <= 0;				// Valor inicial del clk_f
		clk_8f <= 0;			// Valor inicial del clk_8f
	end
	always #1 clk_8f <= ~clk_8f;		// toggle cada 1ns -> 8f = 500MHz
	always #8 clk_f <= ~clk_f;			// toggle cada 8ns -> f = 62,5MHz
endmodule

serialtopar/serialtopar_synth.v
/* Generated by Yosys 0.7 (git sha1 61f6811, gcc 5.4.0-6ubuntu1~16.04.4 -O2 -fstack-protector-strong -fPIC -Os) */

(* top =  1  *)
(* src = "serialtopar_synth.v:9" *)
module serialtopar_synth(data_out, valid_out, clk_f, clk_8f, reset_L, data_in);
  (* src = "serialtopar_synth.v:34" *)
  wire _00_;
  (* src = "serialtopar_synth.v:34" *)
  wire [2:0] _01_;
  (* src = "serialtopar_synth.v:24" *)
  wire [7:0] _02_;
  (* src = "serialtopar_synth.v:34" *)
  wire _03_;
  wire _04_;
  wire _05_;
  wire _06_;
  wire _07_;
  wire _08_;
  wire _09_;
  wire _10_;
  wire _11_;
  wire _12_;
  wire _13_;
  wire _14_;
  wire _15_;
  wire _16_;
  wire _17_;
  wire _18_;
  wire _19_;
  wire _20_;
  wire _21_;
  wire _22_;
  wire _23_;
  wire _24_;
  wire _25_;
  wire _26_;
  wire _27_;
  wire _28_;
  wire _29_;
  wire _30_;
  wire _31_;
  wire _32_;
  wire _33_;
  wire _34_;
  (* src = "serialtopar_synth.v:17" *)
  wire active;
  (* src = "serialtopar_synth.v:19" *)
  wire [2:0] bc_cnt;
  (* src = "serialtopar_synth.v:18" *)
  wire [7:0] buffer;
  (* src = "serialtopar_synth.v:13" *)
  input clk_8f;
  (* src = "serialtopar_synth.v:12" *)
  input clk_f;
  (* src = "serialtopar_synth.v:15" *)
  input data_in;
  (* src = "serialtopar_synth.v:10" *)
  output [7:0] data_out;
  (* src = "serialtopar_synth.v:14" *)
  input reset_L;
  (* src = "serialtopar_synth.v:20" *)
  wire [7:0] shift_reg;
  (* src = "serialtopar_synth.v:11" *)
  output valid_out;
  NOT _35_ (
    .A(reset_L),
    .Y(_04_)
  );
  NOR _36_ (
    .A(active),
    .B(bc_cnt[2]),
    .Y(_05_)
  );
  NOR _37_ (
    .A(_05_),
    .B(_04_),
    .Y(_00_)
  );
  NOT _38_ (
    .A(buffer[4]),
    .Y(_06_)
  );
  NOT _39_ (
    .A(buffer[5]),
    .Y(_07_)
  );
  NOR _40_ (
    .A(_07_),
    .B(_06_),
    .Y(_08_)
  );
  NOT _41_ (
    .A(buffer[6]),
    .Y(_09_)
  );
  NOT _42_ (
    .A(data_in),
    .Y(_10_)
  );
  NOR _43_ (
    .A(_10_),
    .B(_09_),
    .Y(_11_)
  );
  NAND _44_ (
    .A(_11_),
    .B(_08_),
    .Y(_12_)
  );
  NOR _45_ (
    .A(buffer[2]),
    .B(buffer[1]),
    .Y(_13_)
  );
  NOT _46_ (
    .A(buffer[3]),
    .Y(_14_)
  );
  NOR _47_ (
    .A(_14_),
    .B(buffer[7]),
    .Y(_15_)
  );
  NAND _48_ (
    .A(_15_),
    .B(_13_),
    .Y(_16_)
  );
  NOR _49_ (
    .A(_16_),
    .B(_12_),
    .Y(_17_)
  );
  NAND _50_ (
    .A(_17_),
    .B(reset_L),
    .Y(_18_)
  );
  NOR _51_ (
    .A(_18_),
    .B(bc_cnt[0]),
    .Y(_01_[0])
  );
  NOT _52_ (
    .A(bc_cnt[0]),
    .Y(_19_)
  );
  NOT _53_ (
    .A(bc_cnt[1]),
    .Y(_20_)
  );
  NAND _54_ (
    .A(_20_),
    .B(_19_),
    .Y(_21_)
  );
  NAND _55_ (
    .A(bc_cnt[1]),
    .B(bc_cnt[0]),
    .Y(_22_)
  );
  NAND _56_ (
    .A(_22_),
    .B(_21_),
    .Y(_23_)
  );
  NOR _57_ (
    .A(_23_),
    .B(_18_),
    .Y(_01_[1])
  );
  NOT _58_ (
    .A(bc_cnt[2]),
    .Y(_24_)
  );
  NOT _59_ (
    .A(_22_),
    .Y(_25_)
  );
  NOR _60_ (
    .A(_25_),
    .B(_24_),
    .Y(_26_)
  );
  NOR _61_ (
    .A(_22_),
    .B(bc_cnt[2]),
    .Y(_27_)
  );
  NOR _62_ (
    .A(_27_),
    .B(_26_),
    .Y(_28_)
  );
  NOR _63_ (
    .A(_28_),
    .B(_18_),
    .Y(_01_[2])
  );
  NOT _64_ (
    .A(valid_out),
    .Y(_29_)
  );
  NAND _65_ (
    .A(_05_),
    .B(_29_),
    .Y(_30_)
  );
  NAND _66_ (
    .A(_30_),
    .B(reset_L),
    .Y(_31_)
  );
  NOR _67_ (
    .A(_31_),
    .B(_17_),
    .Y(_03_)
  );
  NOT _68_ (
    .A(buffer[1]),
    .Y(_32_)
  );
  NOR _69_ (
    .A(_04_),
    .B(_32_),
    .Y(_02_[0])
  );
  NOT _70_ (
    .A(buffer[2]),
    .Y(_33_)
  );
  NOR _71_ (
    .A(_04_),
    .B(_33_),
    .Y(_02_[1])
  );
  NOR _72_ (
    .A(_14_),
    .B(_04_),
    .Y(_02_[2])
  );
  NOR _73_ (
    .A(_06_),
    .B(_04_),
    .Y(_02_[3])
  );
  NOR _74_ (
    .A(_07_),
    .B(_04_),
    .Y(_02_[4])
  );
  NOR _75_ (
    .A(_09_),
    .B(_04_),
    .Y(_02_[5])
  );
  NOT _76_ (
    .A(buffer[7]),
    .Y(_34_)
  );
  NOR _77_ (
    .A(_04_),
    .B(_34_),
    .Y(_02_[6])
  );
  NOR _78_ (
    .A(_10_),
    .B(_04_),
    .Y(_02_[7])
  );
  DFF _79_ (
    .C(clk_f),
    .D(_02_[0]),
    .Q(data_out[0])
  );
  DFF _80_ (
    .C(clk_f),
    .D(_02_[1]),
    .Q(data_out[1])
  );
  DFF _81_ (
    .C(clk_f),
    .D(_02_[2]),
    .Q(data_out[2])
  );
  DFF _82_ (
    .C(clk_f),
    .D(_02_[3]),
    .Q(data_out[3])
  );
  DFF _83_ (
    .C(clk_f),
    .D(_02_[4]),
    .Q(data_out[4])
  );
  DFF _84_ (
    .C(clk_f),
    .D(_02_[5]),
    .Q(data_out[5])
  );
  DFF _85_ (
    .C(clk_f),
    .D(_02_[6]),
    .Q(data_out[6])
  );
  DFF _86_ (
    .C(clk_f),
    .D(_02_[7]),
    .Q(data_out[7])
  );
  DFF _87_ (
    .C(clk_f),
    .D(_03_),
    .Q(valid_out)
  );
  DFF _88_ (
    .C(clk_f),
    .D(_00_),
    .Q(active)
  );
  DFF _89_ (
    .C(clk_f),
    .D(_01_[0]),
    .Q(bc_cnt[0])
  );
  DFF _90_ (
    .C(clk_f),
    .D(_01_[1]),
    .Q(bc_cnt[1])
  );
  DFF _91_ (
    .C(clk_f),
    .D(_01_[2]),
    .Q(bc_cnt[2])
  );
  DFF _92_ (
    .C(clk_8f),
    .D(_02_[1]),
    .Q(buffer[1])
  );
  DFF _93_ (
    .C(clk_8f),
    .D(_02_[2]),
    .Q(buffer[2])
  );
  DFF _94_ (
    .C(clk_8f),
    .D(_02_[3]),
    .Q(buffer[3])
  );
  DFF _95_ (
    .C(clk_8f),
    .D(_02_[4]),
    .Q(buffer[4])
  );
  DFF _96_ (
    .C(clk_8f),
    .D(_02_[5]),
    .Q(buffer[5])
  );
  DFF _97_ (
    .C(clk_8f),
    .D(_02_[6]),
    .Q(buffer[6])
  );
  DFF _98_ (
    .C(clk_8f),
    .D(_02_[7]),
    .Q(buffer[7])
  );
  assign shift_reg = { data_in, buffer[7:1] };
endmodule

serialtopar/serialtopar.v
/*
 *Universidad de Costa Rica - Escuela de Ingenieria Electrica
 *Proyecto #1 - IE-0523 - modulo serialtopar
 *@author Giancarlo Marin H.
 *@date   20/05/2019
 *@brief  Descripcion conductual del modulo serial to paralelo con bit de valido en las entradas y la salida
*/

module serialtopar(
	output reg[7:0]	data_out,		// salida en paralelo de 8b
	output reg 		valid_out,		// bit de valid de la salida
	input 			clk_f,			// señal de clock del modulo
	input			clk_8f,			// señal de clock a 8f
	input 			reset_L,		// señal de reset del modulo
	input 			data_in 		// entrada de datos serial
	);
	reg 			active;		    // regs internos de 1 bit
	reg [7:0]		buffer;// reg desplazante que recibe los datos
	reg [2:0]		bc_cnt;			// reg que cuenta la cantidad de datos de control bc
	wire [7:0]		shift_reg;

	assign shift_reg = {data_in,buffer[7:1]};

	always @(posedge clk_8f) begin		// bloque sincrono
		if (!reset_L) begin			// reset de los flops 
			buffer <= 0;
			data_out <= 0;
			valid_out <= 0;
			bc_cnt <= 0;
			active <= 0;
		end
		else begin
			buffer <= shift_reg;
		end
    end	

    always @(posedge clk_f) begin		// bloque sincrono
		if (!reset_L) begin			// reset de los flops 
			
		end
		else begin					// asignacion de los flops de manera sincrona
			data_out<=shift_reg;			
			if (shift_reg==8'hbc)begin
				bc_cnt <= bc_cnt +1;
				valid_out <= 0;
			end
			else begin
				bc_cnt <= 0;
			end
			if (bc_cnt >= 4) begin
				active = 1;
			end
			if (active && shift_reg!=8'hbc)begin
			valid_out <= 1;
			end
		end	
    end
endmodule

byte_stripping/tb.v
/*
 *Universidad de Costa Rica - Escuela de Ingenieria Electrica
 *Proyecto #1 - IE-0523 - modulo tb del serialtopar
 *@author Giancarlo Marin H.
 *@date   20/05/2019
 *@brief  Banco de pruebas del serialtopar con su respectivo probador
*/

`timescale 	1ns				/ 100ps		// escala
// includes de archivos de verilog
`include "serialtopar.v"
`include "serialtopar_synth.v"
`include "probador.v"
`include "cmos_cells.v"

module tb(); // Testbench
	//wires de interconexion del modulo y su probador
	wire[7:0] 	data_out_c, data_out_e;
	wire 		clk_f, clk_8f, reset_L, data_in, valid_out_c, valid_out_e;

	// Instanciacion de modulos con los parametros definidos
	serialtopar s2p_con(/*autoinst*/
			.data_out(data_out_c[7:0]),
			.valid_out(valid_out_c),
			.clk_f(clk_f),
			.clk_8f(clk_8f),
			.reset_L(reset_L),
			.data_in(data_in));

	serialtopar_synth s2p_est(/*autoinst*/
			.data_out(data_out_e[7:0]),
			.valid_out(valid_out_e),
			.clk_8f(clk_8f),
			.clk_f(clk_f),
			.data_in(data_in),
			.reset_L(reset_L));
		
	probador test (/*autoinst*/
			.clk_f(clk_f),
			.clk_8f(clk_8f),
			.reset_L(reset_L),
			.data_in(data_in),
			.data_out_c(data_out_c[7:0]),
			.data_out_e(data_out_e[7:0]),
			.valid_out_c(valid_out_c),
			.valid_out_e(valid_out_e));
endmodule

byte_stripping/cmos_cells.v
module BUF(input A,output Y);
assign Y = A;
endmodule

module NOT(input A,output Y);
assign Y = ~A;
endmodule

module NAND(input A, input B, output Y);
assign Y = ~(A & B);
endmodule

module NOR(input A, input B, output Y);
assign Y = ~(A | B);
endmodule

module DFF(input C, input D, output reg Q);
always @(posedge C)
	Q <= D;
endmodule

module DFFSR(input C, input D, input S, input R, output reg Q);
always @(posedge C, posedge S, posedge R)
	if (S)
		Q <= 1'b1;
	else if (R)
		Q <= 1'b0;
	else
		Q <= D;
endmodule

serialtopar/s2p.vcd
$date
	Wed May 22 20:30:06 2019
$end
$version
	Icarus Verilog
$end
$timescale
	100ps
$end
$scope module BUF $end
$var wire 1 ! A $end
$var wire 1 " Y $end
$upscope $end
$scope module DFFSR $end
$var wire 1 # C $end
$var wire 1 $ D $end
$var wire 1 % R $end
$var wire 1 & S $end
$var reg 1 ' Q $end
$upscope $end
$scope module tb $end
$var wire 1 ( valid_out_e $end
$var wire 1 ) valid_out_c $end
$var wire 1 * reset_L $end
$var wire 8 + data_out_e [7:0] $end
$var wire 8 , data_out_c [7:0] $end
$var wire 1 - data_in $end
$var wire 1 . clk_f $end
$var wire 1 / clk_8f $end
$scope module s2p_con $end
$var wire 8 0 shift_reg [7:0] $end
$var wire 1 * reset_L $end
$var wire 1 - data_in $end
$var wire 1 . clk_f $end
$var wire 1 / clk_8f $end
$var reg 1 1 active $end
$var reg 3 2 bc_cnt [2:0] $end
$var reg 8 3 buffer [7:0] $end
$var reg 8 4 data_out [7:0] $end
$var reg 1 ) valid_out $end
$upscope $end
$scope module s2p_est $end
$var wire 1 ( valid_out $end
$var wire 8 5 shift_reg [7:0] $end
$var wire 1 * reset_L $end
$var wire 8 6 data_out [7:0] $end
$var wire 1 - data_in $end
$var wire 1 . clk_f $end
$var wire 1 / clk_8f $end
$var wire 8 7 buffer [7:0] $end
$var wire 3 8 bc_cnt [2:0] $end
$var wire 1 9 active $end
$var wire 1 : _34_ $end
$var wire 1 ; _33_ $end
$var wire 1 < _32_ $end
$var wire 1 = _31_ $end
$var wire 1 > _30_ $end
$var wire 1 ? _29_ $end
$var wire 1 @ _28_ $end
$var wire 1 A _27_ $end
$var wire 1 B _26_ $end
$var wire 1 C _25_ $end
$var wire 1 D _24_ $end
$var wire 1 E _23_ $end
$var wire 1 F _22_ $end
$var wire 1 G _21_ $end
$var wire 1 H _20_ $end
$var wire 1 I _19_ $end
$var wire 1 J _18_ $end
$var wire 1 K _17_ $end
$var wire 1 L _16_ $end
$var wire 1 M _15_ $end
$var wire 1 N _14_ $end
$var wire 1 O _13_ $end
$var wire 1 P _12_ $end
$var wire 1 Q _11_ $end
$var wire 1 R _10_ $end
$var wire 1 S _09_ $end
$var wire 1 T _08_ $end
$var wire 1 U _07_ $end
$var wire 1 V _06_ $end
$var wire 1 W _05_ $end
$var wire 1 X _04_ $end
$var wire 1 Y _03_ $end
$var wire 8 Z _02_ [7:0] $end
$var wire 3 [ _01_ [2:0] $end
$var wire 1 \ _00_ $end
$scope module _35_ $end
$var wire 1 X Y $end
$var wire 1 * A $end
$upscope $end
$scope module _36_ $end
$var wire 1 ] B $end
$var wire 1 W Y $end
$var wire 1 9 A $end
$upscope $end
$scope module _37_ $end
$var wire 1 W A $end
$var wire 1 X B $end
$var wire 1 \ Y $end
$upscope $end
$scope module _38_ $end
$var wire 1 ^ A $end
$var wire 1 V Y $end
$upscope $end
$scope module _39_ $end
$var wire 1 _ A $end
$var wire 1 U Y $end
$upscope $end
$scope module _40_ $end
$var wire 1 U A $end
$var wire 1 V B $end
$var wire 1 T Y $end
$upscope $end
$scope module _41_ $end
$var wire 1 ` A $end
$var wire 1 S Y $end
$upscope $end
$scope module _42_ $end
$var wire 1 R Y $end
$var wire 1 - A $end
$upscope $end
$scope module _43_ $end
$var wire 1 R A $end
$var wire 1 S B $end
$var wire 1 Q Y $end
$upscope $end
$scope module _44_ $end
$var wire 1 Q A $end
$var wire 1 T B $end
$var wire 1 P Y $end
$upscope $end
$scope module _45_ $end
$var wire 1 a A $end
$var wire 1 b B $end
$var wire 1 O Y $end
$upscope $end
$scope module _46_ $end
$var wire 1 c A $end
$var wire 1 N Y $end
$upscope $end
$scope module _47_ $end
$var wire 1 N A $end
$var wire 1 d B $end
$var wire 1 M Y $end
$upscope $end
$scope module _48_ $end
$var wire 1 M A $end
$var wire 1 O B $end
$var wire 1 L Y $end
$upscope $end
$scope module _49_ $end
$var wire 1 L A $end
$var wire 1 P B $end
$var wire 1 K Y $end
$upscope $end
$scope module _50_ $end
$var wire 1 K A $end
$var wire 1 J Y $end
$var wire 1 * B $end
$upscope $end
$scope module _51_ $end
$var wire 1 J A $end
$var wire 1 e B $end
$var wire 1 f Y $end
$upscope $end
$scope module _52_ $end
$var wire 1 g A $end
$var wire 1 I Y $end
$upscope $end
$scope module _53_ $end
$var wire 1 h A $end
$var wire 1 H Y $end
$upscope $end
$scope module _54_ $end
$var wire 1 H A $end
$var wire 1 I B $end
$var wire 1 G Y $end
$upscope $end
$scope module _55_ $end
$var wire 1 i A $end
$var wire 1 j B $end
$var wire 1 F Y $end
$upscope $end
$scope module _56_ $end
$var wire 1 F A $end
$var wire 1 G B $end
$var wire 1 E Y $end
$upscope $end
$scope module _57_ $end
$var wire 1 E A $end
$var wire 1 J B $end
$var wire 1 k Y $end
$upscope $end
$scope module _58_ $end
$var wire 1 l A $end
$var wire 1 D Y $end
$upscope $end
$scope module _59_ $end
$var wire 1 F A $end
$var wire 1 C Y $end
$upscope $end
$scope module _60_ $end
$var wire 1 C A $end
$var wire 1 D B $end
$var wire 1 B Y $end
$upscope $end
$scope module _61_ $end
$var wire 1 F A $end
$var wire 1 m B $end
$var wire 1 A Y $end
$upscope $end
$scope module _62_ $end
$var wire 1 A A $end
$var wire 1 B B $end
$var wire 1 @ Y $end
$upscope $end
$scope module _63_ $end
$var wire 1 @ A $end
$var wire 1 J B $end
$var wire 1 n Y $end
$upscope $end
$scope module _64_ $end
$var wire 1 ? Y $end
$var wire 1 ( A $end
$upscope $end
$scope module _65_ $end
$var wire 1 W A $end
$var wire 1 ? B $end
$var wire 1 > Y $end
$upscope $end
$scope module _66_ $end
$var wire 1 > A $end
$var wire 1 = Y $end
$var wire 1 * B $end
$upscope $end
$scope module _67_ $end
$var wire 1 = A $end
$var wire 1 K B $end
$var wire 1 Y Y $end
$upscope $end
$scope module _68_ $end
$var wire 1 o A $end
$var wire 1 < Y $end
$upscope $end
$scope module _69_ $end
$var wire 1 X A $end
$var wire 1 < B $end
$var wire 1 p Y $end
$upscope $end
$scope module _70_ $end
$var wire 1 q A $end
$var wire 1 ; Y $end
$upscope $end
$scope module _71_ $end
$var wire 1 X A $end
$var wire 1 ; B $end
$var wire 1 r Y $end
$upscope $end
$scope module _72_ $end
$var wire 1 N A $end
$var wire 1 X B $end
$var wire 1 s Y $end
$upscope $end
$scope module _73_ $end
$var wire 1 V A $end
$var wire 1 X B $end
$var wire 1 t Y $end
$upscope $end
$scope module _74_ $end
$var wire 1 U A $end
$var wire 1 X B $end
$var wire 1 u Y $end
$upscope $end
$scope module _75_ $end
$var wire 1 S A $end
$var wire 1 X B $end
$var wire 1 v Y $end
$upscope $end
$scope module _76_ $end
$var wire 1 w A $end
$var wire 1 : Y $end
$upscope $end
$scope module _77_ $end
$var wire 1 X A $end
$var wire 1 : B $end
$var wire 1 x Y $end
$upscope $end
$scope module _78_ $end
$var wire 1 R A $end
$var wire 1 X B $end
$var wire 1 y Y $end
$upscope $end
$scope module _79_ $end
$var wire 1 z D $end
$var wire 1 . C $end
$var reg 1 { Q $end
$upscope $end
$scope module _80_ $end
$var wire 1 | D $end
$var wire 1 . C $end
$var reg 1 } Q $end
$upscope $end
$scope module _81_ $end
$var wire 1 ~ D $end
$var wire 1 . C $end
$var reg 1 !" Q $end
$upscope $end
$scope module _82_ $end
$var wire 1 "" D $end
$var wire 1 . C $end
$var reg 1 #" Q $end
$upscope $end
$scope module _83_ $end
$var wire 1 $" D $end
$var wire 1 . C $end
$var reg 1 %" Q $end
$upscope $end
$scope module _84_ $end
$var wire 1 &" D $end
$var wire 1 . C $end
$var reg 1 '" Q $end
$upscope $end
$scope module _85_ $end
$var wire 1 (" D $end
$var wire 1 . C $end
$var reg 1 )" Q $end
$upscope $end
$scope module _86_ $end
$var wire 1 *" D $end
$var wire 1 . C $end
$var reg 1 +" Q $end
$upscope $end
$scope module _87_ $end
$var wire 1 Y D $end
$var wire 1 . C $end
$var reg 1 ( Q $end
$upscope $end
$scope module _88_ $end
$var wire 1 \ D $end
$var wire 1 . C $end
$var reg 1 9 Q $end
$upscope $end
$scope module _89_ $end
$var wire 1 ," D $end
$var wire 1 . C $end
$var reg 1 -" Q $end
$upscope $end
$scope module _90_ $end
$var wire 1 ." D $end
$var wire 1 . C $end
$var reg 1 /" Q $end
$upscope $end
$scope module _91_ $end
$var wire 1 0" D $end
$var wire 1 . C $end
$var reg 1 1" Q $end
$upscope $end
$scope module _92_ $end
$var wire 1 2" D $end
$var wire 1 / C $end
$var reg 1 3" Q $end
$upscope $end
$scope module _93_ $end
$var wire 1 4" D $end
$var wire 1 / C $end
$var reg 1 5" Q $end
$upscope $end
$scope module _94_ $end
$var wire 1 6" D $end
$var wire 1 / C $end
$var reg 1 7" Q $end
$upscope $end
$scope module _95_ $end
$var wire 1 8" D $end
$var wire 1 / C $end
$var reg 1 9" Q $end
$upscope $end
$scope module _96_ $end
$var wire 1 :" D $end
$var wire 1 / C $end
$var reg 1 ;" Q $end
$upscope $end
$scope module _97_ $end
$var wire 1 <" D $end
$var wire 1 / C $end
$var reg 1 =" Q $end
$upscope $end
$scope module _98_ $end
$var wire 1 >" D $end
$var wire 1 / C $end
$var reg 1 ?" Q $end
$upscope $end
$upscope $end
$scope module test $end
$var wire 8 @" data_out_c [7:0] $end
$var wire 8 A" data_out_e [7:0] $end
$var wire 1 ) valid_out_c $end
$var wire 1 ( valid_out_e $end
$var wire 1 B" check_valid $end
$var wire 1 C" check_data_out $end
$var reg 1 / clk_8f $end
$var reg 1 . clk_f $end
$var reg 1 - data_in $end
$var reg 1 * reset_L $end
$scope module c0 $end
$var wire 1 . clk $end
$var wire 8 D" data_out_c [7:0] $end
$var wire 8 E" data_out_e [7:0] $end
$var wire 1 * reset_L $end
$var wire 1 ) valid_out_c $end
$var wire 1 ( valid_out_e $end
$var reg 1 C" check_data_out $end
$var reg 1 B" check_valid $end
$var reg 8 F" out_c [7:0] $end
$var reg 8 G" out_e [7:0] $end
$var reg 1 H" valid_c $end
$var reg 1 I" valid_e $end
$upscope $end
$upscope $end
$upscope $end
$enddefinitions $end
#0
$dumpvars
xI"
xH"
bx G"
bx F"
bx E"
bx D"
xC"
xB"
bx A"
bx @"
x?"
0>"
x="
0<"
x;"
0:"
x9"
08"
x7"
06"
x5"
04"
x3"
02"
x1"
00"
x/"
0."
x-"
0,"
x+"
0*"
x)"
0("
x'"
0&"
x%"
0$"
x#"
0""
x!"
0~
x}
0|
x{
0z
0y
0x
xw
0v
0u
0t
0s
0r
xq
0p
xo
0n
xm
xl
0k
xj
xi
xh
xg
0f
xe
xd
xc
xb
xa
x`
x_
x^
x]
0\
b0 [
b0 Z
0Y
1X
xW
xV
xU
xT
xS
1R
0Q
1P
xO
xN
xM
xL
0K
1J
xI
xH
xG
xF
xE
xD
xC
xB
xA
x@
x?
x>
1=
x<
x;
x:
x9
bx 8
bxz 7
bx 6
b0xxxxxxx 5
bx 4
bx 3
bx 2
x1
b0xxxxxxx 0
0/
0.
0-
bx ,
bx +
0*
x)
x(
x'
z&
z%
z$
z#
z"
z!
$end
#10
1L
0M
0T
1O
1<
1;
1N
1V
1U
1S
1:
b0 0
0o
0b
0q
0a
0c
0^
0_
0`
b0 5
0w
0d
b0 3
03"
05"
07"
09"
0;"
0="
b0z 7
0?"
1/
#20
0/
#30
1/
#40
0/
#50
1/
#60
0/
#70
1/
#80
1@
1E
0A
0C
0G
0B
0Y
0>
1F
0\
1W
1I
1H
1D
1=
1?
0j
0g
0e
0i
0h
0m
0l
0]
0X
01
b0 2
0)
b0 ,
b0 4
b0 @"
b0 D"
0{
0}
0!"
0#"
0%"
0'"
0)"
b0 +
b0 6
b0 A"
b0 E"
0+"
0(
09
0-"
0/"
b0 8
01"
0I"
0H"
b0 G"
b0 F"
1B"
1C"
1*
0/
1.
#90
1/
#100
0/
#110
1/
#120
0/
#130
1*"
1>"
b10000000 Z
1y
0R
b10000000 5
b10000000 0
1-
1/
#140
0/
#150
1("
1<"
b11000000 Z
1x
0:
b11000000 5
1w
1d
b11000000 0
b1000000z 7
1?"
b10000000 3
1/
#160
0/
0.
#170
1&"
1:"
1Q
b11100000 Z
1v
0S
b11100000 0
b11100000 5
1`
b11000000 3
b1100000z 7
1="
1/
#180
0/
#190
1$"
18"
b11110000 Z
1u
0U
b11110000 5
1_
b11110000 0
b1110000z 7
1;"
b11100000 3
1/
#200
0/
#210
1""
16"
1T
1t
0*"
0>"
0Q
b1111000 Z
0y
0V
1^
1R
b11110000 3
b1111000z 7
19"
b1111000 5
b1111000 0
0-
1/
#220
0/
#230
1,"
b1 [
1f
0J
1K
0P
0("
0<"
0L
1~
14"
1*"
1>"
0x
1s
1Q
b10111100 Z
1y
1M
1:
0N
0R
0w
0d
1c
b10111100 5
b10111100 0
1-
0?"
b111100z 7
17"
b1111000 3
1/
#240
1."
1k
0E
1G
0,"
b10 [
0f
0I
1j
1g
1e
b1 8
1-"
1+"
1'"
1%"
1#"
b10111100 +
b10111100 6
b10111100 A"
b10111100 E"
1!"
b1 2
b10111100 ,
b10111100 4
b10111100 @"
b10111100 D"
0/
1.
#250
0."
b0 [
0k
1J
0K
1|
12"
0&"
0:"
1("
1<"
1L
1P
1r
0v
1x
0*"
0>"
0O
0M
0Q
b1011110 Z
0y
0;
1S
0:
1q
1a
0`
1w
1d
1R
b10111100 3
15"
0="
b1011110z 7
1?"
b1011110 5
b1011110 0
0-
1/
#260
0/
#270
0("
0<"
1&"
1:"
0$"
08"
1z
0x
1v
0T
0u
b101111 Z
1p
1M
1:
0S
1U
0<
0w
0d
1`
0_
b101111 5
1o
1b
b101111 0
0?"
1="
0;"
b101111z 7
13"
b1011110 3
1/
#280
0/
