serialtopar/checker.v
/*
 *Universidad de Costa Rica - Escuela de Ingenieria Electrica
 *Proyecto #1 - IE-0523 - modulo checker del mux
 *@author Giancarlo Marin H.
 *@date   14/05/2019
 *@brief  Modulo de chequeo entre las señales de dos mux uno conductual y otro estructural
*/

module checker(
	output reg		check_data_out,	// salida de 1 bit que indica que ambos datos de data_out son iguales	
	output reg 		check_valid,	// salida de 1 bit que indica que ambos bits de valido son iguales
	input 			clk,			// señal de clock del modulo	
	input 			reset_L,		// señal de reset_L del modulo
	input [7:0]		data_out_c,		// entrada de datos generada por del modulo conductual
	input [7:0]		data_out_e,		// entrada de datos generada por el modulo estructural
	input 			valid_out_c,	// entrada de bit de valido por el modulo conductual
	input 			valid_out_e	// entrada de bit de valido por el modulo estructural
	);
	// ffs de entrada 
	reg [7:0] 		out_c,out_e; 	
	reg 			valid_c,valid_e;
	
	always @(posedge clk) begin		// ffs para registrar las entradas
		if(reset_L==0) begin
			out_c <= 0;
			out_e <= 0;
			valid_c <= 0;
			valid_e <= 0;
		end else begin
			out_c <= data_out_c;
			out_e <= data_out_e;
			valid_c <= valid_out_c;
			valid_e <= valid_out_e;
		end
	end

	always @(posedge clk) begin		// bloque de comparacion en los flancos de reloj
		if (reset_L==1) begin
			if (out_c == out_e) begin
				check_data_out<=1;
			end
			else begin
				check_data_out<=0;
				$display ($time,"Error diferencia entre modulos");
			end 
			if (valid_c==valid_e) begin
				check_valid<=1;
			end
			else begin
				check_valid<=0;
				$display ($time,"Error diferencia entre modulos");
			end 
		end
		else begin
			check_data_out<=1;
			check_valid<=1;
		end
	end
endmodule // checker

serialtopar/probador.v
/*
 *Universidad de Costa Rica - Escuela de Ingenieria Electrica
 *Proyecto #1 - IE-0523 - modulo probador del serialtopar
 *@author Giancarlo Marin H.
 *@date   20/05/2019
 *@brief  Modulo que genera las señales y monitoriza las salidas del modulo serialtopar conductual y estructural sintetizado
*/

`include "checker.v"

module probador (
	output reg 					clk_f,			// generador del clock
	output reg 					clk_8f,			// generador del clock
	output reg 					reset_L,		// generador de reset
	output reg					data_in,		// generador de la entrada de dato 0
	input [7:0]					data_out_c,		// monitor de salida de datos cond
	input [7:0]					data_out_e,		// monitor de salida de datos estr
	input 						valid_out_c, 	// monitor de salida del bit valido cond
	input 						valid_out_e 	// monitor de salida del bit valido estr
	);
	wire check_data_out, check_valid;	// salidas del checker

	checker c0(/*autoinst*/
			.check_data_out(check_data_out),
			.check_valid(check_valid),
			.clk(clk_f),
			.reset_L(reset_L),
			.data_out_c(data_out_c[7:0]),
			.data_out_e(data_out_e[7:0]),
			.valid_out_c(valid_out_c),
			.valid_out_e(valid_out_e));

	initial begin
		$dumpfile("s2p.vcd");		// archivo "dump"
		$dumpvars;					// dumping de variables
		// Mensajes en consola 
		$display ("\t\tclk\treset_L\tdata_in \tdata_out_c valid_out_c\tdata_out_e valid_out_e\tcheck_data_out check_valid_out");
		$monitor($time,"\t%b\t%b\t%x %b\t%x %b\t%b %b", clk_f, reset_L, data_in, data_out_c, valid_out_c, data_out_e, valid_out_e, check_data_out,check_valid);
		// Pruebas
		data_in <= 0; 					
		// Pruebas #1: Reset bajo. 
		reset_L <= 0;
		// Prueba #2: Reset alto. Valido primer dato
		@(posedge clk_f);
		reset_L <= 1;
		// Prueba #3: Envía BC 4 veces
		repeat(4) begin
			@(posedge clk_8f);
			data_in <= 0;
			@(posedge clk_8f);
			data_in <= 0;
			@(posedge clk_8f);
			data_in <= 1;
			@(posedge clk_8f);
			data_in <= 1;
			@(posedge clk_8f);
			data_in <= 1;
			@(posedge clk_8f);
			data_in <= 1;
			@(posedge clk_8f);
			data_in <= 0;
			@(posedge clk_8f);
			data_in <= 1;
		end
		// Prueba #4: Envía 3 datos validos
		repeat(8) begin // envía FF
			@(posedge clk_8f);
			data_in <= 1;
		end
		// envia EE
		repeat(2) begin
			@(posedge clk_8f);
			data_in <= 0;
			@(posedge clk_8f);
			data_in <= 1;
			@(posedge clk_8f);
			data_in <= 1;
			@(posedge clk_8f);
			data_in <= 1;
		end
		//envia DD
		repeat(2) begin
			@(posedge clk_8f);
			data_in <= 1;
			@(posedge clk_8f);
			data_in <= 0;
			@(posedge clk_8f);
			data_in <= 1;
			@(posedge clk_8f);
			data_in <= 1;
		end
		// Prueba #5: Envía BC de nuevo. Se espera valid_out = 0
		@(posedge clk_8f);
		data_in <= 0;
		@(posedge clk_8f);
		data_in <= 0;
		@(posedge clk_8f);
		data_in <= 1;
		@(posedge clk_8f);
		data_in <= 1;
		@(posedge clk_8f);
		data_in <= 1;
		@(posedge clk_8f);
		data_in <= 1;
		@(posedge clk_8f);
		data_in <= 0;
		@(posedge clk_8f);
		data_in <= 1;
		// Prueba 6: Vuelve a enviar otro dato valido
		// envia AA
		repeat(4) begin
			@(posedge clk_8f);
			data_in <= 0;
			@(posedge clk_8f);
			data_in <= 1;
		end
		// Prueba 7: Reset alto y termina de almacenar señales
		repeat(7) begin
			@(posedge clk_8f);
		end
		reset_L <= 0;
		@(posedge clk_f);
		$finish;	
	end
	// Generador del clk
	initial	begin
		clk_f <= 0;				// Valor inicial del clk_f
		clk_8f <= 0;			// Valor inicial del clk_8f
	end
	always #1 clk_8f <= ~clk_8f;		// toggle cada 1ns -> 8f = 500MHz
	always #8 clk_f <= ~clk_f;			// toggle cada 8ns -> f = 62,5MHz
endmodule

serialtopar/serialtopar_synth.v
/* Generated by Yosys 0.7 (git sha1 61f6811, gcc 5.4.0-6ubuntu1~16.04.4 -O2 -fstack-protector-strong -fPIC -Os) */

(* top =  1  *)
(* src = "serialtopar_synth.v:9" *)
module serialtopar_synth(data_out, valid_out, clk_f, clk_8f, reset_L, data_in);
  (* src = "serialtopar_synth.v:34" *)
  wire _00_;
  (* src = "serialtopar_synth.v:34" *)
  wire [2:0] _01_;
  (* src = "serialtopar_synth.v:24" *)
  wire [7:0] _02_;
  (* src = "serialtopar_synth.v:34" *)
  wire _03_;
  wire _04_;
  wire _05_;
  wire _06_;
  wire _07_;
  wire _08_;
  wire _09_;
  wire _10_;
  wire _11_;
  wire _12_;
  wire _13_;
  wire _14_;
  wire _15_;
  wire _16_;
  wire _17_;
  wire _18_;
  wire _19_;
  wire _20_;
  wire _21_;
  wire _22_;
  wire _23_;
  wire _24_;
  wire _25_;
  wire _26_;
  wire _27_;
  wire _28_;
  wire _29_;
  wire _30_;
  wire _31_;
  wire _32_;
  wire _33_;
  wire _34_;
  (* src = "serialtopar_synth.v:17" *)
  wire active;
  (* src = "serialtopar_synth.v:19" *)
  wire [2:0] bc_cnt;
  (* src = "serialtopar_synth.v:18" *)
  wire [7:0] buffer;
  (* src = "serialtopar_synth.v:13" *)
  input clk_8f;
  (* src = "serialtopar_synth.v:12" *)
  input clk_f;
  (* src = "serialtopar_synth.v:15" *)
  input data_in;
  (* src = "serialtopar_synth.v:10" *)
  output [7:0] data_out;
  (* src = "serialtopar_synth.v:14" *)
  input reset_L;
  (* src = "serialtopar_synth.v:20" *)
  wire [7:0] shift_reg;
  (* src = "serialtopar_synth.v:11" *)
  output valid_out;
  NOT _35_ (
    .A(reset_L),
    .Y(_04_)
  );
  NOR _36_ (
    .A(active),
    .B(bc_cnt[2]),
    .Y(_05_)
  );
  NOR _37_ (
    .A(_05_),
    .B(_04_),
    .Y(_00_)
  );
  NOT _38_ (
    .A(buffer[4]),
    .Y(_06_)
  );
  NOT _39_ (
    .A(buffer[5]),
    .Y(_07_)
  );
  NOR _40_ (
    .A(_07_),
    .B(_06_),
    .Y(_08_)
  );
  NOT _41_ (
    .A(buffer[6]),
    .Y(_09_)
  );
  NOT _42_ (
    .A(data_in),
    .Y(_10_)
  );
  NOR _43_ (
    .A(_10_),
    .B(_09_),
    .Y(_11_)
  );
  NAND _44_ (
    .A(_11_),
    .B(_08_),
    .Y(_12_)
  );
  NOR _45_ (
    .A(buffer[2]),
    .B(buffer[1]),
    .Y(_13_)
  );
  NOT _46_ (
    .A(buffer[3]),
    .Y(_14_)
  );
  NOR _47_ (
    .A(_14_),
    .B(buffer[7]),
    .Y(_15_)
  );
  NAND _48_ (
    .A(_15_),
    .B(_13_),
    .Y(_16_)
  );
  NOR _49_ (
    .A(_16_),
    .B(_12_),
    .Y(_17_)
  );
  NAND _50_ (
    .A(_17_),
    .B(reset_L),
    .Y(_18_)
  );
  NOR _51_ (
    .A(_18_),
    .B(bc_cnt[0]),
    .Y(_01_[0])
  );
  NOT _52_ (
    .A(bc_cnt[0]),
    .Y(_19_)
  );
  NOT _53_ (
    .A(bc_cnt[1]),
    .Y(_20_)
  );
  NAND _54_ (
    .A(_20_),
    .B(_19_),
    .Y(_21_)
  );
  NAND _55_ (
    .A(bc_cnt[1]),
    .B(bc_cnt[0]),
    .Y(_22_)
  );
  NAND _56_ (
    .A(_22_),
    .B(_21_),
    .Y(_23_)
  );
  NOR _57_ (
    .A(_23_),
    .B(_18_),
    .Y(_01_[1])
  );
  NOT _58_ (
    .A(bc_cnt[2]),
    .Y(_24_)
  );
  NOT _59_ (
    .A(_22_),
    .Y(_25_)
  );
  NOR _60_ (
    .A(_25_),
    .B(_24_),
    .Y(_26_)
  );
  NOR _61_ (
    .A(_22_),
    .B(bc_cnt[2]),
    .Y(_27_)
  );
  NOR _62_ (
    .A(_27_),
    .B(_26_),
    .Y(_28_)
  );
  NOR _63_ (
    .A(_28_),
    .B(_18_),
    .Y(_01_[2])
  );
  NOT _64_ (
    .A(valid_out),
    .Y(_29_)
  );
  NAND _65_ (
    .A(_05_),
    .B(_29_),
    .Y(_30_)
  );
  NAND _66_ (
    .A(_30_),
    .B(reset_L),
    .Y(_31_)
  );
  NOR _67_ (
    .A(_31_),
    .B(_17_),
    .Y(_03_)
  );
  NOT _68_ (
    .A(buffer[1]),
    .Y(_32_)
  );
  NOR _69_ (
    .A(_04_),
    .B(_32_),
    .Y(_02_[0])
  );
  NOT _70_ (
    .A(buffer[2]),
    .Y(_33_)
  );
  NOR _71_ (
    .A(_04_),
    .B(_33_),
    .Y(_02_[1])
  );
  NOR _72_ (
    .A(_14_),
    .B(_04_),
    .Y(_02_[2])
  );
  NOR _73_ (
    .A(_06_),
    .B(_04_),
    .Y(_02_[3])
  );
  NOR _74_ (
    .A(_07_),
    .B(_04_),
    .Y(_02_[4])
  );
  NOR _75_ (
    .A(_09_),
    .B(_04_),
    .Y(_02_[5])
  );
  NOT _76_ (
    .A(buffer[7]),
    .Y(_34_)
  );
  NOR _77_ (
    .A(_04_),
    .B(_34_),
    .Y(_02_[6])
  );
  NOR _78_ (
    .A(_10_),
    .B(_04_),
    .Y(_02_[7])
  );
  DFF _79_ (
    .C(clk_f),
    .D(_02_[0]),
    .Q(data_out[0])
  );
  DFF _80_ (
    .C(clk_f),
    .D(_02_[1]),
    .Q(data_out[1])
  );
  DFF _81_ (
    .C(clk_f),
    .D(_02_[2]),
    .Q(data_out[2])
  );
  DFF _82_ (
    .C(clk_f),
    .D(_02_[3]),
    .Q(data_out[3])
  );
  DFF _83_ (
    .C(clk_f),
    .D(_02_[4]),
    .Q(data_out[4])
  );
  DFF _84_ (
    .C(clk_f),
    .D(_02_[5]),
    .Q(data_out[5])
  );
  DFF _85_ (
    .C(clk_f),
    .D(_02_[6]),
    .Q(data_out[6])
  );
  DFF _86_ (
    .C(clk_f),
    .D(_02_[7]),
    .Q(data_out[7])
  );
  DFF _87_ (
    .C(clk_f),
    .D(_03_),
    .Q(valid_out)
  );
  DFF _88_ (
    .C(clk_f),
    .D(_00_),
    .Q(active)
  );
  DFF _89_ (
    .C(clk_f),
    .D(_01_[0]),
    .Q(bc_cnt[0])
  );
  DFF _90_ (
    .C(clk_f),
    .D(_01_[1]),
    .Q(bc_cnt[1])
  );
  DFF _91_ (
    .C(clk_f),
    .D(_01_[2]),
    .Q(bc_cnt[2])
  );
  DFF _92_ (
    .C(clk_8f),
    .D(_02_[1]),
    .Q(buffer[1])
  );
  DFF _93_ (
    .C(clk_8f),
    .D(_02_[2]),
    .Q(buffer[2])
  );
  DFF _94_ (
    .C(clk_8f),
    .D(_02_[3]),
    .Q(buffer[3])
  );
  DFF _95_ (
    .C(clk_8f),
    .D(_02_[4]),
    .Q(buffer[4])
  );
  DFF _96_ (
    .C(clk_8f),
    .D(_02_[5]),
    .Q(buffer[5])
  );
  DFF _97_ (
    .C(clk_8f),
    .D(_02_[6]),
    .Q(buffer[6])
  );
  DFF _98_ (
    .C(clk_8f),
    .D(_02_[7]),
    .Q(buffer[7])
  );
  assign shift_reg = { data_in, buffer[7:1] };
endmodule

serialtopar/serialtopar.v
/*
 *Universidad de Costa Rica - Escuela de Ingenieria Electrica
 *Proyecto #1 - IE-0523 - modulo serialtopar
 *@author Giancarlo Marin H.
 *@date   20/05/2019
 *@brief  Descripcion conductual del modulo serial to paralelo con bit de valido en las entradas y la salida
*/

module serialtopar(
	output reg[7:0]	data_out,		// salida en paralelo de 8b
	output reg 		valid_out,		// bit de valid de la salida
	input 			clk_f,			// señal de clock del modulo
	input			clk_8f,			// señal de clock a 8f
	input 			reset_L,		// señal de reset del modulo
	input 			data_in 		// entrada de datos serial
	);
	reg 			active;		    // regs internos de 1 bit
	reg [7:0]		buffer;// reg desplazante que recibe los datos
	reg [2:0]		bc_cnt;			// reg que cuenta la cantidad de datos de control bc
	wire [7:0]		shift_reg;

	assign shift_reg = {data_in,buffer[7:1]};

	always @(posedge clk_8f) begin		// bloque sincrono
		if (!reset_L) begin			// reset de los flops 
			buffer <= 0;
			data_out <= 0;
			valid_out <= 0;
			bc_cnt <= 0;
			active <= 0;
		end
		else begin
			buffer <= shift_reg;
		end
    end	

    always @(posedge clk_f) begin		// bloque sincrono
		if (!reset_L) begin			// reset de los flops 
			
		end
		else begin					// asignacion de los flops de manera sincrona
			data_out<=shift_reg;			
			if (shift_reg==8'hbc)begin
				bc_cnt <= bc_cnt +1;
				valid_out <= 0;
			end
			else begin
				bc_cnt <= 0;
			end
			if (bc_cnt >= 4) begin
				active = 1;
			end
			if (active && shift_reg!=8'hbc)begin
			valid_out <= 1;
			end
		end	
    end
endmodule

byte_stripping/tb.v
/*
 *Universidad de Costa Rica - Escuela de Ingenieria Electrica
 *Proyecto #1 - IE-0523 - modulo tb del serialtopar
 *@author Giancarlo Marin H.
 *@date   20/05/2019
 *@brief  Banco de pruebas del serialtopar con su respectivo probador
*/

`timescale 	1ns				/ 100ps		// escala
// includes de archivos de verilog
`include "serialtopar.v"
`include "serialtopar_synth.v"
`include "probador.v"
`include "cmos_cells.v"

module tb(); // Testbench
	//wires de interconexion del modulo y su probador
	wire[7:0] 	data_out_c, data_out_e;
	wire 		clk_f, clk_8f, reset_L, data_in, valid_out_c, valid_out_e;

	// Instanciacion de modulos con los parametros definidos
	serialtopar s2p_con(/*autoinst*/
			.data_out(data_out_c[7:0]),
			.valid_out(valid_out_c),
			.clk_f(clk_f),
			.clk_8f(clk_8f),
			.reset_L(reset_L),
			.data_in(data_in));

	serialtopar_synth s2p_est(/*autoinst*/
			.data_out(data_out_e[7:0]),
			.valid_out(valid_out_e),
			.clk_8f(clk_8f),
			.clk_f(clk_f),
			.data_in(data_in),
			.reset_L(reset_L));
		
	probador test (/*autoinst*/
			.clk_f(clk_f),
			.clk_8f(clk_8f),
			.reset_L(reset_L),
			.data_in(data_in),
			.data_out_c(data_out_c[7:0]),
			.data_out_e(data_out_e[7:0]),
			.valid_out_c(valid_out_c),
			.valid_out_e(valid_out_e));
endmodule

byte_stripping/cmos_cells.v
module BUF(input A,output Y);
assign Y = A;
endmodule

module NOT(input A,output Y);
assign Y = ~A;
endmodule

module NAND(input A, input B, output Y);
assign Y = ~(A & B);
endmodule

module NOR(input A, input B, output Y);
assign Y = ~(A | B);
endmodule

module DFF(input C, input D, output reg Q);
always @(posedge C)
	Q <= D;
endmodule

module DFFSR(input C, input D, input S, input R, output reg Q);
always @(posedge C, posedge S, posedge R)
	if (S)
		Q <= 1'b1;
	else if (R)
		Q <= 1'b0;
	else
		Q <= D;
endmodule

serialtopar/s2p.vcd
$date
	Mon May 20 23:57:35 2019
$end
$version
	Icarus Verilog
$end
$timescale
	100ps
$end
$scope module BUF $end
$var wire 1 ! A $end
$var wire 1 " Y $end
$upscope $end
$scope module DFF $end
$var wire 1 # C $end
$var wire 1 $ D $end
$var reg 1 % Q $end
$upscope $end
$scope module DFFSR $end
$var wire 1 & C $end
$var wire 1 ' D $end
$var wire 1 ( R $end
$var wire 1 ) S $end
$var reg 1 * Q $end
$upscope $end
$scope module NAND $end
$var wire 1 + A $end
$var wire 1 , B $end
$var wire 1 - Y $end
$upscope $end
$scope module NOR $end
$var wire 1 . A $end
$var wire 1 / B $end
$var wire 1 0 Y $end
$upscope $end
$scope module NOT $end
$var wire 1 1 A $end
$var wire 1 2 Y $end
$upscope $end
$scope module tb $end
$var wire 8 3 data_out_e [7:0] $end
$var wire 1 4 valid_out_e $end
$var wire 1 5 valid_out_c $end
$var wire 1 6 reset_L $end
$var wire 8 7 data_out_c [7:0] $end
$var wire 1 8 data_in $end
$var wire 1 9 clk_f $end
$var wire 1 : clk_8f $end
$scope module s2p_con $end
$var wire 8 ; shift_reg [7:0] $end
$var wire 1 6 reset_L $end
$var wire 1 8 data_in $end
$var wire 1 9 clk_f $end
$var wire 1 : clk_8f $end
$var reg 1 < active $end
$var reg 3 = bc_cnt [2:0] $end
$var reg 8 > buffer [7:0] $end
$var reg 8 ? data_out [7:0] $end
$var reg 1 5 valid_out $end
$upscope $end
$scope module s2p_est $end
$var wire 8 @ buffer [7:0] $end
$var wire 8 A data_out [7:0] $end
$var wire 1 4 valid_out $end
$var wire 8 B shift_reg [7:0] $end
$var wire 1 6 reset_L $end
$var wire 1 8 data_in $end
$var wire 1 9 clk_f $end
$var wire 1 : clk_8f $end
$upscope $end
$scope module test $end
$var wire 8 C data_out_c [7:0] $end
$var wire 8 D data_out_e [7:0] $end
$var wire 1 5 valid_out_c $end
$var wire 1 4 valid_out_e $end
$var wire 1 E check_valid $end
$var wire 1 F check_data_out $end
$var reg 1 : clk_8f $end
$var reg 1 9 clk_f $end
$var reg 1 8 data_in $end
$var reg 1 6 reset_L $end
$scope module c0 $end
$var wire 1 9 clk $end
$var wire 8 G data_out_c [7:0] $end
$var wire 8 H data_out_e [7:0] $end
$var wire 1 6 reset_L $end
$var wire 1 5 valid_out_c $end
$var wire 1 4 valid_out_e $end
$var reg 1 F check_data_out $end
$var reg 1 E check_valid $end
$var reg 8 I out_c [7:0] $end
$var reg 8 J out_e [7:0] $end
$var reg 1 K valid_c $end
$var reg 1 L valid_e $end
$upscope $end
$upscope $end
$upscope $end
$enddefinitions $end
#0
$dumpvars
xL
xK
bx J
bx I
b0 H
bx G
xF
xE
b0 D
bx C
b0zzzzzzz B
b0 A
bz @
bx ?
bx >
bx =
x<
b0xxxxxxx ;
0:
09
08
bx 7
06
x5
04
b0 3
z2
z1
x0
z/
z.
x-
z,
z+
x*
z)
z(
z'
z&
x%
z$
z#
z"
z!
$end
#10
b0 ;
0<
b0 =
05
b0 7
b0 ?
b0 C
b0 G
b0 >
1:
#20
0:
#30
1:
#40
0:
#50
1:
#60
0:
#70
1:
#80
0L
0K
b0 J
b0 I
1E
1F
16
0:
19
#90
1:
#100
0:
#110
1:
#120
0:
#130
b1zzzzzzz B
b10000000 ;
18
1:
#140
0:
#150
b11000000 ;
b10000000 >
1:
#160
0:
09
#170
b11100000 ;
b11000000 >
1:
#180
0:
#190
b11110000 ;
b11100000 >
1:
#200
0:
#210
b11110000 >
b0zzzzzzz B
b1111000 ;
08
1:
#220
0:
#230
b1zzzzzzz B
b10111100 ;
18
b1111000 >
1:
#240
b1 =
b10111100 7
b10111100 ?
b10111100 C
b10111100 G
0:
19
#250
b10111100 >
b0zzzzzzz B
b1011110 ;
08
1:
#260
0:
#270
b101111 ;
b1011110 >
1:
#280
0:
#290
b101111 >
b1zzzzzzz B
b10010111 ;
18
1:
#300
0:
#310
b11001011 ;
b10010111 >
1:
#320
0:
09
#330
b11100101 ;
b11001011 >
1:
#340
0:
#350
b11110010 ;
b11100101 >
1:
#360
0:
#370
b11110010 >
b0zzzzzzz B
b1111001 ;
08
1:
#380
0:
#390
b1zzzzzzz B
b10111100 ;
18
b1111001 >
1:
#400
b10 =
b10111100 I
0:
19
#410
b10111100 >
b0zzzzzzz B
b1011110 ;
08
1:
#420
0:
#430
b101111 ;
b1011110 >
1:
#440
0:
#450
b101111 >
b1zzzzzzz B
b10010111 ;
18
1:
#460
0:
#470
b11001011 ;
b10010111 >
1:
#480
0:
09
#490
b11100101 ;
b11001011 >
1:
#500
0:
#510
b11110010 ;
b11100101 >
1:
#520
0:
#530
b11110010 >
b0zzzzzzz B
b1111001 ;
08
1:
#540
0:
#550
b1zzzzzzz B
b10111100 ;
18
b1111001 >
1:
#560
0F
b11 =
0:
19
#570
b10111100 >
b0zzzzzzz B
b1011110 ;
08
1:
#580
0:
#590
b101111 ;
b1011110 >
1:
#600
0:
#610
b101111 >
b1zzzzzzz B
b10010111 ;
18
1:
#620
0:
#630
b11001011 ;
b10010111 >
1:
#640
0:
09
#650
b11100101 ;
b11001011 >
1:
#660
0:
#670
b11110010 ;
b11100101 >
1:
#680
0:
#690
b11110010 >
b0zzzzzzz B
b1111001 ;
08
1:
#700
0:
#710
b1zzzzzzz B
b10111100 ;
18
b1111001 >
1:
#720
b100 =
0:
19
#730
b11011110 ;
b10111100 >
1:
#740
0:
#750
b11101111 ;
b11011110 >
1:
#760
0:
#770
b11110111 ;
b11101111 >
1:
#780
0:
#790
b11111011 ;
b11110111 >
1:
#800
0:
09
#810
b11111101 ;
b11111011 >
1:
#820
0:
#830
b11111110 ;
b11111101 >
1:
#840
0:
#850
b11111111 ;
b11111110 >
1:
#860
0:
#870
b11111111 >
1:
#880
15
b0 =
b11111111 7
b11111111 ?
b11111111 C
b11111111 G
1<
0:
19
#890
b0zzzzzzz B
b1111111 ;
08
1:
#900
0:
#910
b1zzzzzzz B
b10111111 ;
18
b1111111 >
1:
#920
0:
#930
b11011111 ;
b10111111 >
1:
#940
0:
#950
b11101111 ;
b11011111 >
1:
#960
0:
09
#970
b11101111 >
b0zzzzzzz B
b1110111 ;
08
1:
#980
0:
#990
b1zzzzzzz B
b10111011 ;
18
b1110111 >
1:
#1000
0:
#1010
b11011101 ;
b10111011 >
1:
#1020
0:
#1030
b11101110 ;
b11011101 >
1:
#1040
b11101110 7
b11101110 ?
b11101110 C
b11101110 G
1K
b11111111 I
0:
19
#1050
b11110111 ;
b11101110 >
1:
#1060
0:
#1070
b0zzzzzzz B
b1111011 ;
08
b11110111 >
1:
#1080
0:
#1090
b1111011 >
b1zzzzzzz B
b10111101 ;
18
1:
#1100
0:
#1110
b11011110 ;
b10111101 >
1:
#1120
0:
09
#1130
b11101111 ;
b11011110 >
1:
#1140
0:
#1150
b0zzzzzzz B
b1110111 ;
08
b11101111 >
1:
#1160
0:
#1170
b1110111 >
b1zzzzzzz B
b10111011 ;
18
1:
#1180
0:
#1190
b11011101 ;
b10111011 >
1:
#1200
0E
b11101110 I
b11011101 7
b11011101 ?
b11011101 C
b11011101 G
0:
19
#1210
b11011101 >
b0zzzzzzz B
b1101110 ;
08
1:
#1220
0:
#1230
b110111 ;
b1101110 >
1:
#1240
0:
#1250
b110111 >
b1zzzzzzz B
b10011011 ;
18
1:
#1260
0:
#1270
b11001101 ;
b10011011 >
1:
#1280
0:
09
#1290
b11100110 ;
b11001101 >
1:
#1300
0:
#1310
b11110011 ;
b11100110 >
1:
#1320
0:
#1330
b11110011 >
b0zzzzzzz B
b1111001 ;
08
1:
#1340
0:
#1350
b1zzzzzzz B
b10111100 ;
18
b1111001 >
1:
#1360
05
b1 =
b10111100 7
b10111100 ?
b10111100 C
b10111100 G
b11011101 I
0:
19
#1370
b10111100 >
b0zzzzzzz B
b1011110 ;
08
1:
#1380
0:
#1390
b1zzzzzzz B
b10101111 ;
18
b1011110 >
1:
#1400
0:
#1410
b10101111 >
b0zzzzzzz B
b1010111 ;
08
1:
#1420
0:
#1430
b1zzzzzzz B
b10101011 ;
18
b1010111 >
1:
#1440
0:
09
#1450
b10101011 >
b0zzzzzzz B
b1010101 ;
08
1:
#1460
0:
#1470
b1zzzzzzz B
b10101010 ;
18
b1010101 >
1:
#1480
0:
#1490
b10101010 >
b0zzzzzzz B
b1010101 ;
08
1:
#1500
0:
#1510
b1zzzzzzz B
b10101010 ;
18
b1010101 >
1:
#1520
0K
b10111100 I
15
b0 =
b10101010 7
b10101010 ?
b10101010 C
b10101010 G
0:
19
#1530
b11010101 ;
b10101010 >
1:
#1540
0:
#1550
b11101010 ;
b11010101 >
1:
#1560
0:
#1570
b11110101 ;
b11101010 >
1:
#1580
0:
#1590
b11111010 ;
b11110101 >
1:
#1600
0:
09
#1610
b11111101 ;
b11111010 >
1:
#1620
0:
#1630
b11111110 ;
b11111101 >
1:
#1640
0:
#1650
b11111111 ;
b11111110 >
06
1:
#1660
0:
#1670
b10000000 ;
0<
05
b0 7
b0 ?
b0 C
b0 G
b0 >
1:
#1680
b0 I
1E
1F
0:
19
