demux/checker.v
/*
 *Universidad de Costa Rica - Escuela de Ingenieria Electrica
 *Proyecto #1 - IE-0523 - modulo demux
 *@author Giancarlo Marin H.
 *@date   15/05/2019
 *@brief  Modulo de chequeo entre las señales de dos demux 1 a 2 de 7bit con selector automatico y bits de valido
*/

module checker(
	output reg		check_out0,		// salida de 1 bit que indica que ambos datos de la salida 0 son iguales	
	output reg		check_out1,		// salida de 1 bit que indica que ambos datos de la salida 1 son iguales	
	input 			clk,			// señal de clock del modulo	
	input 			reset_L,		// señal de reset_L del modulo
	input [7:0]		data_out0_c,	// salida 0 del demultiplexor conductual
	input [7:0]		data_out1_c,	// salida 1 del demultiplexor conductual
	input [7:0]		data_out0_e,			// salida 0 del demultiplexor estructural
	input [7:0]		data_out1_e			// salida 1 del demultiplexor estructural
	);
	reg [7:0] 		out_c_0,out_e_0,out_c_1,out_e_1; //ff
	
	always @(posedge clk) begin		// ffs para registrar las entradas
		if(reset_L==0) begin
			out_c_0 <= 0;
			out_c_1 <= 0;
			out_e_0 <= 0;
			out_e_1 <= 0;
		end else begin
			out_c_0 <= data_out0_c;
			out_c_1 <= data_out1_c;
			out_e_0 <= data_out0_e;
			out_e_1 <= data_out1_e;
		end
	end

	always @(posedge clk) begin		// bloque de comparacion en los flancos de reloj
		if (reset_L==1) begin
			if (out_c_0==out_e_0) begin
				check_out0<=1;
			end
			else begin
				check_out0<=0;
				$display ($time,"Error diferencia entre modulos");
			end 
			if (out_c_1==out_e_1) begin
				check_out1<=1;
			end
			else begin
				check_out1<=0;
				$display ($time,"Error diferencia entre modulos");
			end 
		end
		else begin
			check_out0<=1;
			check_out1<=1;
		end
	end
endmodule // checker_mux

demux/probador.v
/*
 *Universidad de Costa Rica - Escuela de Ingenieria Electrica
 *Proyecto #1 - IE-0523 - modulo probador del demux
 *@author Giancarlo Marin H.
 *@date   15/05/2019
 *@brief  Modulo que genera las señales y monitoriza las salidas del modulo mux conductual y estructural sintetizado
*/

`include "checker.v"

module probador (
	output reg 					clk,			// generador del clock
	output reg 					reset_L,		// generador de reset
	output reg[7:0]				data_in,		// generador de la entrada de dato 0
	output reg 					valid_in,		// generador de bit valido entrada 0
	input [7:0]					data_out0_c,	// monitor de salida 0 de datos cond
	input [7:0]					data_out0_e,	// monitor de salida 0 de datos estr
	input 						valid_out0_c, 	// monitor de salida del bit valido 0 cond
	input 						valid_out0_e, 	// monitor de salida del bit valido 0 estr
	input [7:0]					data_out1_c,	// monitor de salida 1 de datos cond
	input [7:0]					data_out1_e,	// monitor de salida 1 de datos estr
	input 						valid_out1_c, 	// monitor de salida del bit valido 1 cond
	input 						valid_out1_e 	// monitor de salida del bit valido 1 estr
	);
	wire check_out0, check_out1, check_valid_out0, check_valid_out1;	// salidas del checker

	checker c0(/*autoinst*/
			.check_out0(check_out0),
			.check_out1(check_out1),
			.clk(clk),
			.reset_L(reset_L),
			.data_out0_c(data_out0_c[7:0]),
			.data_out1_c(data_out1_c[7:0]),
			.data_out0_e(data_out0_e[7:0]),
			.data_out1_e(data_out1_e[7:0]));

	initial begin
		$dumpfile("demux.vcd");		// archivo "dump"
		$dumpvars;					// dumping de variables
		// Mensajes en consola 
		$display ("\t\tclk\treset_L\tdata_in valid_in\tcheck_out0 check_out1");
		$monitor($time,"\t%b\t%b\t%x %b\t%x %b\t%b %b", clk, reset_L, data_in, valid_in, check_out0,check_out1);
		// Pruebas
		valid_in <= 0;
		data_in <= 7'b0; 					
		// Pruebas #1: Reset bajo. 
		reset_L <= 0;
		// Prueba #2: Reset alto. Valido primer dato
		@(posedge clk);
		reset_L <= 1;
		// Sincroniza
		@(posedge clk);
		valid_in <= 1;
		data_in <= 8'hff;
		repeat(3) begin
			@(posedge clk) begin
				data_in <= data_in - 8'h11;
			end
		end
		// Prueba #3: Espera
		@(posedge clk) begin
			valid_in <= 0;
		end
		@(posedge clk);
		@(posedge clk);
		// Prueba #4: Continua la entrada de dato_in por dos ciclos mas
		@(posedge clk) begin
			valid_in <= 1;
			data_in <= 8'h03;
		end
		@(posedge clk) begin
			data_in <= 8'h04;
		end
		@(posedge clk) begin
			valid_in <= 0;
		end
		@(posedge clk);
		@(posedge clk);
		// Prueba #5: Prueba del funcionamiento de selector interno con entrada de mas datos
		@(posedge clk) begin
			valid_in <= 1;
			data_in <= 8'haa;
		end
		@(posedge clk) begin
			data_in <= 8'h99;
		end
		@(posedge clk) begin
			valid_in <= 0;
		end
		@(posedge clk);
		@(posedge clk);
		// Prueba #6: Ultima entrada de datos
		@(posedge clk) begin
			valid_in <= 1;
			data_in <= 8'h07;
		end
		@(posedge clk) begin
			data_in <= 8'h08;
		end
		@(posedge clk) begin
			valid_in <= 0;
		end
		@(posedge clk);
		@(posedge clk);
		// Prueba 7: Reset alto y termina de almacenar señales
		@(posedge clk);
		reset_L <= 0;
		#10 $finish;	
	end
	// Generador del clk
	initial	clk <= 0;				// Valor inicial del clk
	always #10 clk <= ~clk;			// toggle cada 10ns
endmodule

demux/demux_synth.v
/* Generated by Yosys 0.7 (git sha1 61f6811, gcc 5.4.0-6ubuntu1~16.04.4 -O2 -fstack-protector-strong -fPIC -Os) */

(* top =  1  *)
(* src = "demux_synth.v:9" *)
module demux_synth(data_out0, data_out1, valid_out0, valid_out1, valid_in, clk, reset_L, data_in);
  wire _00_;
  wire _01_;
  wire _02_;
  wire _03_;
  wire _04_;
  wire _05_;
  wire _06_;
  wire _07_;
  wire _08_;
  wire _09_;
  wire _10_;
  wire _11_;
  wire _12_;
  wire _13_;
  wire _14_;
  wire _15_;
  wire _16_;
  wire _17_;
  wire _18_;
  wire _19_;
  wire _20_;
  wire _21_;
  wire _22_;
  wire _23_;
  wire _24_;
  wire _25_;
  wire _26_;
  wire _27_;
  wire _28_;
  wire _29_;
  wire _30_;
  wire _31_;
  wire _32_;
  wire _33_;
  (* src = "demux_synth.v:15" *)
  input clk;
  (* src = "demux_synth.v:17" *)
  input [7:0] data_in;
  (* src = "demux_synth.v:10" *)
  output [7:0] data_out0;
  (* src = "demux_synth.v:11" *)
  output [7:0] data_out1;
  (* src = "demux_synth.v:20" *)
  wire [7:0] data_reg0;
  (* src = "demux_synth.v:16" *)
  input reset_L;
  (* src = "demux_synth.v:14" *)
  input valid_in;
  (* src = "demux_synth.v:12" *)
  output valid_out0;
  (* src = "demux_synth.v:13" *)
  output valid_out1;
  NOT _34_ (
    .A(valid_in),
    .Y(_00_)
  );
  NOT _35_ (
    .A(reset_L),
    .Y(_01_)
  );
  NOR _36_ (
    .A(_01_),
    .B(_00_),
    .Y(valid_out0)
  );
  NOR _37_ (
    .A(data_reg0[0]),
    .B(valid_in),
    .Y(_02_)
  );
  NOT _38_ (
    .A(data_in[0]),
    .Y(_03_)
  );
  NAND _39_ (
    .A(_03_),
    .B(valid_in),
    .Y(_04_)
  );
  NAND _40_ (
    .A(_04_),
    .B(reset_L),
    .Y(_05_)
  );
  NOR _41_ (
    .A(_05_),
    .B(_02_),
    .Y(data_out0[0])
  );
  NOR _42_ (
    .A(valid_in),
    .B(data_reg0[1]),
    .Y(_06_)
  );
  NOT _43_ (
    .A(data_in[1]),
    .Y(_07_)
  );
  NAND _44_ (
    .A(valid_in),
    .B(_07_),
    .Y(_08_)
  );
  NAND _45_ (
    .A(_08_),
    .B(reset_L),
    .Y(_09_)
  );
  NOR _46_ (
    .A(_09_),
    .B(_06_),
    .Y(data_out0[1])
  );
  NOR _47_ (
    .A(data_reg0[2]),
    .B(valid_in),
    .Y(_10_)
  );
  NOT _48_ (
    .A(data_in[2]),
    .Y(_11_)
  );
  NAND _49_ (
    .A(_11_),
    .B(valid_in),
    .Y(_12_)
  );
  NAND _50_ (
    .A(_12_),
    .B(reset_L),
    .Y(_13_)
  );
  NOR _51_ (
    .A(_13_),
    .B(_10_),
    .Y(data_out0[2])
  );
  NOR _52_ (
    .A(data_reg0[3]),
    .B(valid_in),
    .Y(_14_)
  );
  NOT _53_ (
    .A(data_in[3]),
    .Y(_15_)
  );
  NAND _54_ (
    .A(_15_),
    .B(valid_in),
    .Y(_16_)
  );
  NAND _55_ (
    .A(_16_),
    .B(reset_L),
    .Y(_17_)
  );
  NOR _56_ (
    .A(_17_),
    .B(_14_),
    .Y(data_out0[3])
  );
  NOR _57_ (
    .A(data_reg0[4]),
    .B(valid_in),
    .Y(_18_)
  );
  NOT _58_ (
    .A(data_in[4]),
    .Y(_19_)
  );
  NAND _59_ (
    .A(_19_),
    .B(valid_in),
    .Y(_20_)
  );
  NAND _60_ (
    .A(_20_),
    .B(reset_L),
    .Y(_21_)
  );
  NOR _61_ (
    .A(_21_),
    .B(_18_),
    .Y(data_out0[4])
  );
  NOR _62_ (
    .A(data_reg0[5]),
    .B(valid_in),
    .Y(_22_)
  );
  NOT _63_ (
    .A(data_in[5]),
    .Y(_23_)
  );
  NAND _64_ (
    .A(_23_),
    .B(valid_in),
    .Y(_24_)
  );
  NAND _65_ (
    .A(_24_),
    .B(reset_L),
    .Y(_25_)
  );
  NOR _66_ (
    .A(_25_),
    .B(_22_),
    .Y(data_out0[5])
  );
  NOR _67_ (
    .A(data_reg0[6]),
    .B(valid_in),
    .Y(_26_)
  );
  NOT _68_ (
    .A(data_in[6]),
    .Y(_27_)
  );
  NAND _69_ (
    .A(_27_),
    .B(valid_in),
    .Y(_28_)
  );
  NAND _70_ (
    .A(_28_),
    .B(reset_L),
    .Y(_29_)
  );
  NOR _71_ (
    .A(_29_),
    .B(_26_),
    .Y(data_out0[6])
  );
  NOR _72_ (
    .A(data_reg0[7]),
    .B(valid_in),
    .Y(_30_)
  );
  NOT _73_ (
    .A(data_in[7]),
    .Y(_31_)
  );
  NAND _74_ (
    .A(_31_),
    .B(valid_in),
    .Y(_32_)
  );
  NAND _75_ (
    .A(_32_),
    .B(reset_L),
    .Y(_33_)
  );
  NOR _76_ (
    .A(_33_),
    .B(_30_),
    .Y(data_out0[7])
  );
  DFF _77_ (
    .C(clk),
    .D(data_out0[0]),
    .Q(data_reg0[0])
  );
  DFF _78_ (
    .C(clk),
    .D(data_out0[1]),
    .Q(data_reg0[1])
  );
  DFF _79_ (
    .C(clk),
    .D(data_out0[2]),
    .Q(data_reg0[2])
  );
  DFF _80_ (
    .C(clk),
    .D(data_out0[3]),
    .Q(data_reg0[3])
  );
  DFF _81_ (
    .C(clk),
    .D(data_out0[4]),
    .Q(data_reg0[4])
  );
  DFF _82_ (
    .C(clk),
    .D(data_out0[5]),
    .Q(data_reg0[5])
  );
  DFF _83_ (
    .C(clk),
    .D(data_out0[6]),
    .Q(data_reg0[6])
  );
  DFF _84_ (
    .C(clk),
    .D(data_out0[7]),
    .Q(data_reg0[7])
  );
  assign data_out1 = 8'b00000000;
  assign valid_out1 = 1'b0;
endmodule

demux/demux.v
/*
 *Universidad de Costa Rica - Escuela de Ingenieria Electrica
 *Proyecto #1 - IE-0523 - modulo demux
 *@author Giancarlo Marin H.
 *@date   15/05/2019
 *@brief  Descripcion conductual del modulo demux 1:2 con entrada de 8 bits y bit de valido en la entrada y salidas
*/

module demux(
	output reg[7:0]	data_out0,		// salida 0 de tipo reg del demultiplexor
	output reg[7:0]	data_out1,		// salida 1 de tipo reg del demultiplexor
	output reg 		valid_out0,		// salida 0 bit de valid 
	output reg 		valid_out1,		// salida 1 bit de valid
	input 			valid_in,		// entrada de datos valid
	input 			clk,			// señal de clock del modulo
	input 			reset_L,		// señal de reset en bajo del modulo
	input [7:0]		data_in			// señal entrada de datos del demultiplexor
	);
	reg 			selector,valid0,valid1,reading,toggle;		// regs internos de un 1b 
	reg [7:0]		data_reg0, data_reg1;	// regs internos que transfieren la entrada a la salida y soluciona el problema de temporizacion
	
	always @(*) begin				// bloque combinacional
		data_out0 = 'b0;			// valores por defecto para evitar latches				
		data_out1 = 'b0;
		valid_out0=0;
		valid_out1=0;
		reading=0;
		if (reset_L == 0) begin		// reset asincrono
			data_out0 = 'b0;				
			data_out1 = 'b0;
			valid_out0=0;
			valid_out1=0;
			toggle=0;
		end
		else if (selector == 0 & valid_in == 1) begin	// mux selector para las salidas del demux
			data_out0 = data_in;
			data_out1 = data_reg1;
			valid_out0=1;
			valid_out1=0;
			reading=1;
		end
		else if (selector == 1 & valid_in == 1) begin
			data_out0 = data_reg0;
			data_out1 = data_in;
			valid_out0=0;
			valid_out1=1;
			reading=1;
		end
		else begin
			data_out0 = data_reg0;
			data_out1 = data_reg1;
			valid_out0=0;
			valid_out1=0;
			reading=0;
		end
	end

	always @(negedge reading) begin
		toggle = 1;
	end

	always @(posedge reading) begin
		toggle = 0;
	end

    always @(posedge clk) begin		// bloque sincrono
		if (reset_L == 0) begin		// reset de los flops 
			selector <= 0;
			data_reg0 <= data_out0;
    		data_reg1 <= data_out1;
    		valid0 <= 0;
    		valid1 <= 0;
		end
		else begin					// asignacion de los flops de manera sincrona
			if (toggle) begin
				selector <= ~selector; // toggle del selector cuando 
			end
			else begin
				selector <= selector;
			end
			data_reg0 <= data_out0;	
    		data_reg1 <= data_out1;
    		valid0 <= valid_out0;
    		valid1 <= valid_out1;
		end
    end
endmodule

demux/tb.v
/*
 *Universidad de Costa Rica - Escuela de Ingenieria Electrica
 *Proyecto #1 - IE-0523 - modulo tb del demux
 *@author Giancarlo Marin H.
 *@date   15/05/2019
 *@brief  Banco de pruebas del demux con su respectivo probador
*/

`timescale 	1ns				/ 100ps		// escala
// includes de archivos de verilog
`include "demux.v"
`include "demux_synth.v"
`include "probador.v"
`include "cmos_cells.v"

module tb(); // Testbench
	//wires de interconexion del modulo y su probador
	wire[7:0] 	data_in, data_out0_c, data_out0_e, data_out1_c, data_out1_e;
	wire 		clk, reset_L, valid_in, valid_out0_c, valid_out0_e, valid_out1_c, valid_out1_e;

	// Instanciacion de modulos con los parametros definidos
	demux mux_con(/*autoinst*/
			.data_out0(data_out0_c[7:0]),
			.data_out1(data_out1_c[7:0]),
			.valid_out0(valid_out0_c),
			.valid_out1(valid_out1_c),
			.valid_in(valid_in),
			.clk(clk),
			.reset_L(reset_L),
			.data_in(data_in[7:0]));

	demux_synth mux_est(/*autoinst*/
			.data_out0(data_out0_e[7:0]),
			.data_out1(data_out1_e[7:0]),
			.valid_out0(valid_out0_e),
			.valid_out1(valid_out1_e),
			.clk(clk),
			.data_in(data_in[7:0]),
			.reset_L(reset_L),
			.valid_in(valid_in));
		
	probador test (/*autoinst*/
			.clk(clk),
			.reset_L(reset_L),
			.data_in(data_in[7:0]),
			.valid_in(valid_in),
			.data_out0_c(data_out0_c[7:0]),
			.data_out0_e(data_out0_e[7:0]),
			.valid_out0_c(valid_out0_c),
			.valid_out0_e(valid_out0_e),
			.data_out1_c(data_out1_c[7:0]),
			.data_out1_e(data_out1_e[7:0]),
			.valid_out1_c(valid_out1_c),
			.valid_out1_e(valid_out1_e));
endmodule

byte_stripping/cmos_cells.v
module BUF(input A,output Y);
assign Y = A;
endmodule

module NOT(input A,output Y);
assign Y = ~A;
endmodule

module NAND(input A, input B, output Y);
assign Y = ~(A & B);
endmodule

module NOR(input A, input B, output Y);
assign Y = ~(A | B);
endmodule

module DFF(input C, input D, output reg Q);
always @(posedge C)
	Q <= D;
endmodule

module DFFSR(input C, input D, input S, input R, output reg Q);
always @(posedge C, posedge S, posedge R)
	if (S)
		Q <= 1'b1;
	else if (R)
		Q <= 1'b0;
	else
		Q <= D;
endmodule

demux/demux.vcd
$date
	Wed May 15 18:04:45 2019
$end
$version
	Icarus Verilog
$end
$timescale
	100ps
$end
$scope module BUF $end
$var wire 1 ! A $end
$var wire 1 " Y $end
$upscope $end
$scope module DFFSR $end
$var wire 1 # C $end
$var wire 1 $ D $end
$var wire 1 % R $end
$var wire 1 & S $end
$var reg 1 ' Q $end
$upscope $end
$scope module tb $end
$var wire 8 ( data_out1_e [7:0] $end
$var wire 1 ) valid_out1_e $end
$var wire 1 * valid_out1_c $end
$var wire 1 + valid_out0_e $end
$var wire 1 , valid_out0_c $end
$var wire 1 - valid_in $end
$var wire 1 . reset_L $end
$var wire 8 / data_out1_c [7:0] $end
$var wire 8 0 data_out0_e [7:0] $end
$var wire 8 1 data_out0_c [7:0] $end
$var wire 8 2 data_in [7:0] $end
$var wire 1 3 clk $end
$scope module mux_con $end
$var wire 1 - valid_in $end
$var wire 1 . reset_L $end
$var wire 8 4 data_in [7:0] $end
$var wire 1 3 clk $end
$var reg 8 5 data_out0 [7:0] $end
$var reg 8 6 data_out1 [7:0] $end
$var reg 8 7 data_reg0 [7:0] $end
$var reg 8 8 data_reg1 [7:0] $end
$var reg 1 9 reading $end
$var reg 1 : selector $end
$var reg 1 ; toggle $end
$var reg 1 < valid0 $end
$var reg 1 = valid1 $end
$var reg 1 , valid_out0 $end
$var reg 1 * valid_out1 $end
$upscope $end
$scope module mux_est $end
$var wire 8 > data_out1 [7:0] $end
$var wire 1 ) valid_out1 $end
$var wire 1 + valid_out0 $end
$var wire 1 - valid_in $end
$var wire 1 . reset_L $end
$var wire 8 ? data_reg0 [7:0] $end
$var wire 8 @ data_out0 [7:0] $end
$var wire 8 A data_in [7:0] $end
$var wire 1 3 clk $end
$var wire 1 B _33_ $end
$var wire 1 C _32_ $end
$var wire 1 D _31_ $end
$var wire 1 E _30_ $end
$var wire 1 F _29_ $end
$var wire 1 G _28_ $end
$var wire 1 H _27_ $end
$var wire 1 I _26_ $end
$var wire 1 J _25_ $end
$var wire 1 K _24_ $end
$var wire 1 L _23_ $end
$var wire 1 M _22_ $end
$var wire 1 N _21_ $end
$var wire 1 O _20_ $end
$var wire 1 P _19_ $end
$var wire 1 Q _18_ $end
$var wire 1 R _17_ $end
$var wire 1 S _16_ $end
$var wire 1 T _15_ $end
$var wire 1 U _14_ $end
$var wire 1 V _13_ $end
$var wire 1 W _12_ $end
$var wire 1 X _11_ $end
$var wire 1 Y _10_ $end
$var wire 1 Z _09_ $end
$var wire 1 [ _08_ $end
$var wire 1 \ _07_ $end
$var wire 1 ] _06_ $end
$var wire 1 ^ _05_ $end
$var wire 1 _ _04_ $end
$var wire 1 ` _03_ $end
$var wire 1 a _02_ $end
$var wire 1 b _01_ $end
$var wire 1 c _00_ $end
$scope module _34_ $end
$var wire 1 c Y $end
$var wire 1 - A $end
$upscope $end
$scope module _35_ $end
$var wire 1 b Y $end
$var wire 1 . A $end
$upscope $end
$scope module _36_ $end
$var wire 1 b A $end
$var wire 1 c B $end
$var wire 1 + Y $end
$upscope $end
$scope module _37_ $end
$var wire 1 d A $end
$var wire 1 a Y $end
$var wire 1 - B $end
$upscope $end
$scope module _38_ $end
$var wire 1 e A $end
$var wire 1 ` Y $end
$upscope $end
$scope module _39_ $end
$var wire 1 ` A $end
$var wire 1 _ Y $end
$var wire 1 - B $end
$upscope $end
$scope module _40_ $end
$var wire 1 _ A $end
$var wire 1 ^ Y $end
$var wire 1 . B $end
$upscope $end
$scope module _41_ $end
$var wire 1 ^ A $end
$var wire 1 a B $end
$var wire 1 f Y $end
$upscope $end
$scope module _42_ $end
$var wire 1 g B $end
$var wire 1 ] Y $end
$var wire 1 - A $end
$upscope $end
$scope module _43_ $end
$var wire 1 h A $end
$var wire 1 \ Y $end
$upscope $end
$scope module _44_ $end
$var wire 1 \ B $end
$var wire 1 [ Y $end
$var wire 1 - A $end
$upscope $end
$scope module _45_ $end
$var wire 1 [ A $end
$var wire 1 Z Y $end
$var wire 1 . B $end
$upscope $end
$scope module _46_ $end
$var wire 1 Z A $end
$var wire 1 ] B $end
$var wire 1 i Y $end
$upscope $end
$scope module _47_ $end
$var wire 1 j A $end
$var wire 1 Y Y $end
$var wire 1 - B $end
$upscope $end
$scope module _48_ $end
$var wire 1 k A $end
$var wire 1 X Y $end
$upscope $end
$scope module _49_ $end
$var wire 1 X A $end
$var wire 1 W Y $end
$var wire 1 - B $end
$upscope $end
$scope module _50_ $end
$var wire 1 W A $end
$var wire 1 V Y $end
$var wire 1 . B $end
$upscope $end
$scope module _51_ $end
$var wire 1 V A $end
$var wire 1 Y B $end
$var wire 1 l Y $end
$upscope $end
$scope module _52_ $end
$var wire 1 m A $end
$var wire 1 U Y $end
$var wire 1 - B $end
$upscope $end
$scope module _53_ $end
$var wire 1 n A $end
$var wire 1 T Y $end
$upscope $end
$scope module _54_ $end
$var wire 1 T A $end
$var wire 1 S Y $end
$var wire 1 - B $end
$upscope $end
$scope module _55_ $end
$var wire 1 S A $end
$var wire 1 R Y $end
$var wire 1 . B $end
$upscope $end
$scope module _56_ $end
$var wire 1 R A $end
$var wire 1 U B $end
$var wire 1 o Y $end
$upscope $end
$scope module _57_ $end
$var wire 1 p A $end
$var wire 1 Q Y $end
$var wire 1 - B $end
$upscope $end
$scope module _58_ $end
$var wire 1 q A $end
$var wire 1 P Y $end
$upscope $end
$scope module _59_ $end
$var wire 1 P A $end
$var wire 1 O Y $end
$var wire 1 - B $end
$upscope $end
$scope module _60_ $end
$var wire 1 O A $end
$var wire 1 N Y $end
$var wire 1 . B $end
$upscope $end
$scope module _61_ $end
$var wire 1 N A $end
$var wire 1 Q B $end
$var wire 1 r Y $end
$upscope $end
$scope module _62_ $end
$var wire 1 s A $end
$var wire 1 M Y $end
$var wire 1 - B $end
$upscope $end
$scope module _63_ $end
$var wire 1 t A $end
$var wire 1 L Y $end
$upscope $end
$scope module _64_ $end
$var wire 1 L A $end
$var wire 1 K Y $end
$var wire 1 - B $end
$upscope $end
$scope module _65_ $end
$var wire 1 K A $end
$var wire 1 J Y $end
$var wire 1 . B $end
$upscope $end
$scope module _66_ $end
$var wire 1 J A $end
$var wire 1 M B $end
$var wire 1 u Y $end
$upscope $end
$scope module _67_ $end
$var wire 1 v A $end
$var wire 1 I Y $end
$var wire 1 - B $end
$upscope $end
$scope module _68_ $end
$var wire 1 w A $end
$var wire 1 H Y $end
$upscope $end
$scope module _69_ $end
$var wire 1 H A $end
$var wire 1 G Y $end
$var wire 1 - B $end
$upscope $end
$scope module _70_ $end
$var wire 1 G A $end
$var wire 1 F Y $end
$var wire 1 . B $end
$upscope $end
$scope module _71_ $end
$var wire 1 F A $end
$var wire 1 I B $end
$var wire 1 x Y $end
$upscope $end
$scope module _72_ $end
$var wire 1 y A $end
$var wire 1 E Y $end
$var wire 1 - B $end
$upscope $end
$scope module _73_ $end
$var wire 1 z A $end
$var wire 1 D Y $end
$upscope $end
$scope module _74_ $end
$var wire 1 D A $end
$var wire 1 C Y $end
$var wire 1 - B $end
$upscope $end
$scope module _75_ $end
$var wire 1 C A $end
$var wire 1 B Y $end
$var wire 1 . B $end
$upscope $end
$scope module _76_ $end
$var wire 1 B A $end
$var wire 1 E B $end
$var wire 1 { Y $end
$upscope $end
$scope module _77_ $end
$var wire 1 | D $end
$var wire 1 3 C $end
$var reg 1 } Q $end
$upscope $end
$scope module _78_ $end
$var wire 1 ~ D $end
$var wire 1 3 C $end
$var reg 1 !" Q $end
$upscope $end
$scope module _79_ $end
$var wire 1 "" D $end
$var wire 1 3 C $end
$var reg 1 #" Q $end
$upscope $end
$scope module _80_ $end
$var wire 1 $" D $end
$var wire 1 3 C $end
$var reg 1 %" Q $end
$upscope $end
$scope module _81_ $end
$var wire 1 &" D $end
$var wire 1 3 C $end
$var reg 1 '" Q $end
$upscope $end
$scope module _82_ $end
$var wire 1 (" D $end
$var wire 1 3 C $end
$var reg 1 )" Q $end
$upscope $end
$scope module _83_ $end
$var wire 1 *" D $end
$var wire 1 3 C $end
$var reg 1 +" Q $end
$upscope $end
$scope module _84_ $end
$var wire 1 ," D $end
$var wire 1 3 C $end
$var reg 1 -" Q $end
$upscope $end
$upscope $end
$scope module test $end
$var wire 8 ." data_out0_c [7:0] $end
$var wire 8 /" data_out0_e [7:0] $end
$var wire 8 0" data_out1_c [7:0] $end
$var wire 8 1" data_out1_e [7:0] $end
$var wire 1 , valid_out0_c $end
$var wire 1 + valid_out0_e $end
$var wire 1 * valid_out1_c $end
$var wire 1 ) valid_out1_e $end
$var wire 1 2" check_out1 $end
$var wire 1 3" check_out0 $end
$var reg 1 3 clk $end
$var reg 8 4" data_in [7:0] $end
$var reg 1 . reset_L $end
$var reg 1 - valid_in $end
$scope module c0 $end
$var wire 1 3 clk $end
$var wire 8 5" data_out0_c [7:0] $end
$var wire 8 6" data_out0_e [7:0] $end
$var wire 8 7" data_out1_c [7:0] $end
$var wire 8 8" data_out1_e [7:0] $end
$var wire 1 . reset_L $end
$var reg 1 3" check_out0 $end
$var reg 1 2" check_out1 $end
$var reg 8 9" out_c_0 [7:0] $end
$var reg 8 :" out_c_1 [7:0] $end
$var reg 8 ;" out_e_0 [7:0] $end
$var reg 8 <" out_e_1 [7:0] $end
$upscope $end
$upscope $end
$upscope $end
$enddefinitions $end
#0
$dumpvars
bx <"
bx ;"
bx :"
bx 9"
b0 8"
b0 7"
b0 6"
b0 5"
b0 4"
x3"
x2"
b0 1"
b0 0"
b0 /"
b0 ."
x-"
0,"
x+"
0*"
x)"
0("
x'"
0&"
x%"
0$"
x#"
0""
x!"
0~
x}
0|
0{
0z
xy
0x
0w
xv
0u
0t
xs
0r
0q
xp
0o
0n
xm
0l
0k
xj
0i
0h
xg
0f
0e
xd
1c
1b
xa
1`
1_
1^
x]
1\
1[
1Z
xY
1X
1W
1V
xU
1T
1S
1R
xQ
1P
1O
1N
xM
1L
1K
1J
xI
1H
1G
1F
xE
1D
1C
1B
b0 A
b0 @
bx ?
b0 >
x=
x<
1;
x:
09
bx 8
bx 7
b0 6
b0 5
b0 4
03
b0 2
b0 1
b0 0
b0 /
0.
0-
0,
0+
0*
0)
b0 (
x'
z&
z%
z$
z#
z"
z!
$end
#100
0,"
0*"
0("
0&"
0$"
0""
0~
0|
0{
0x
0u
0r
0o
0l
0i
b0 0
b0 @
b0 /"
b0 6"
0f
1a
1]
1Y
1U
1Q
1M
1I
1E
0B
0F
0J
0N
0R
0V
0Z
0^
0d
0g
0j
0m
0p
0s
0v
0y
0b
0=
0<
b0 8
b0 7
0:
0}
0!"
0#"
0%"
0'"
0)"
0+"
b0 ?
0-"
b0 <"
b0 ;"
b0 :"
b0 9"
12"
13"
1.
13
#200
03
#300
1,"
1*"
1("
1&"
1$"
1""
1~
1|
0B
1{
0F
1x
0J
1u
0N
1r
0R
1o
0V
1l
0Z
1i
0^
b11111111 0
b11111111 @
b11111111 /"
b11111111 6"
1f
1+
0D
0H
0L
0P
0T
0X
0\
0`
1C
0E
1G
0I
1K
0M
1O
0Q
1S
0U
1W
0Y
1[
0]
1_
0a
0;
1z
1w
1t
1q
1n
1k
1h
1e
0c
19
1*
b11111111 /
b11111111 6
b11111111 0"
b11111111 7"
b11111111 2
b11111111 4
b11111111 A
b11111111 4"
1-
1:
13
#400
03
#500
0&"
0|
0r
b11101110 0
b11101110 @
b11101110 /"
b11101110 6"
0f
1N
1^
0O
0_
1P
1`
0;
1d
1g
1j
1m
1p
1s
1v
1y
0q
0e
19
1*
b11101110 /
b11101110 6
b11101110 0"
b11101110 7"
1=
b11111111 8
1}
1!"
1#"
1%"
1'"
1)"
1+"
b11111111 ?
1-"
b11111111 ;"
b11111111 :"
b11101110 2
b11101110 4
b11101110 A
b11101110 4"
13
#600
03
#700
0("
1&"
0~
1|
0u
1r
0i
b11011101 0
b11011101 @
b11011101 /"
b11011101 6"
1f
1J
0N
1Z
0^
0K
1O
0[
1_
1L
0P
1\
0`
0;
0t
1q
0h
1e
0p
0d
19
1*
b11011101 /
b11011101 6
b11011101 0"
b11011101 7"
b11011101 2
b11011101 4
b11011101 A
b11011101 4"
02"
03"
b11101110 ;"
b11101110 :"
0'"
b11101110 ?
0}
b11101110 8
13
#800
03
#900
0&"
0|
0r
b11001100 0
b11001100 @
b11001100 /"
b11001100 6"
0f
1N
1^
0O
0_
1P
1`
0;
1d
0g
1p
0s
0q
0e
19
1*
b11001100 /
b11001100 6
b11001100 0"
b11001100 7"
b11011101 8
1}
0!"
1'"
b11011101 ?
0)"
b11011101 ;"
b11011101 :"
b11001100 2
b11001100 4
b11001100 A
b11001100 4"
13
#1000
03
#1100
0J
0N
0Z
0^
0+
1K
1M
1O
1Q
1[
1]
1_
1a
1;
1c
0p
0d
09
0*
b11001100 /
b11001100 6
b11001100 0"
b11001100 7"
0-
b11001100 ;"
b11001100 :"
0'"
b11001100 ?
0}
b11001100 8
13
#1200
03
#1300
b11001100 /
b11001100 6
b11001100 0"
b11001100 7"
0=
0:
13
#1400
03
#1500
b11001100 /
b11001100 6
b11001100 0"
b11001100 7"
1:
13
#1600
03
#1700
0,"
0*"
0$"
0""
0{
0x
0o
0l
1B
1F
1R
1V
0("
0&"
1~
1|
0C
0G
0S
0W
1J
0u
1N
0r
0Z
1i
0^
b11 0
b11 @
b11 /"
b11 6"
1f
1+
1D
1H
1T
1X
0\
0`
0K
0M
0O
0Q
1[
0]
1_
0a
0;
0z
0w
0n
0k
1h
1e
0c
19
1,
b11 1
b11 5
b11 ."
b11 5"
b11001100 /
b11001100 6
b11001100 0"
b11001100 7"
0:
b11 2
b11 4
b11 A
b11 4"
1-
13
#1800
03
#1900
1""
0~
0|
1l
0i
b100 0
b100 @
b100 /"
b100 6"
0f
0V
1Z
1^
1W
0[
0_
0X
1\
1`
0;
1k
0h
0e
0y
0v
0m
0j
1g
1d
19
1,
b11001100 /
b11001100 6
b11001100 0"
b11001100 7"
b100 1
b100 5
b100 ."
b100 5"
b100 2
b100 4
b100 A
b100 4"
b11 ;"
b11 9"
0-"
0+"
0%"
0#"
1!"
b11 ?
1}
1<
b11 7
13
#2000
03
