gen_clk/probador.v
module probador(
	output reg clk_8f, 
	output reg rst,
	output reg enb,
	input clk_2f_cond,
	input clk_f_cond, 
	input clk_2f_estruct,
	input clk_f_estruct);

reg f2_cond,f2_estruct,f_cond,f_estruct;

 initial begin
       
        $dumpfile("gen_clk.vcd");               //Dumpfile to make in current folder
        $dumpvars;
        
        clk_8f <= 0;
        enb <= 0;                       //                           
        rst <= 1;                       // relojes se resetean            
        
        # 10;
        @(posedge clk_8f)
            rst <= 0;
            enb <= 1;
        
        # 60;
        @(posedge clk_8f)
            enb <= 1;

        # 20;
        @(posedge clk_8f)
            enb <= 0;

        # 20;
        @(posedge clk_8f)
            rst <= 1;
                
        
        # 20;
        @(posedge clk_8f)
            rst <= 0;
            enb <= 1;
        $finish;
end

always @(posedge clk_8f) begin
      f2_cond<=clk_2f_cond;
      f_cond<=clk_f_cond;
      f2_estruct<=clk_2f_estruct;
      f_estruct<=clk_f_estruct;
    if (enb) begin
      if(f_cond==f_estruct)begin
         $display("Las salidas son iguales en f");   
      end
      else begin
        $display("Las salidas NO son iguales en f");   
        end
      if(f2_cond==f2_estruct)begin
         $display("Las salidas son iguales en 2f");   
      end
      else begin
        $display("Las salidas NO son iguales en 2f");   
        end
   end
end

    always # 2 clk_8f <= ~clk_8f;       //genera señal 4 ns 

endmodule

gen_clk/gen_clkSynth.v
/* Generated by Yosys 0.8 (git sha1 UNKNOWN, clang 6.0.0-1ubuntu2 -fPIC -Os) */
`include "./CMOS/cmos_cells.v"

module gen_clkSynth(clk_8f, rst, enb, clk_2f, clk_f);
  wire _00_;
  wire _01_;
  wire [1:0] _02_;
  wire _03_;
  wire _04_;
  wire _05_;
  wire _06_;
  wire _07_;
  wire _08_;
  wire _09_;
  wire _10_;
  wire _11_;
  wire _12_;
  wire _13_;
  wire _14_;
  wire _15_;
  wire _16_;
  wire _17_;
  wire _18_;
  wire _19_;
  output clk_2f;
  input clk_8f;
  output clk_f;
  wire [0:1] counter;
  input enb;
  input rst;
  NOT _20_ (
    .A(rst),
    .Y(_03_)
  );
  NOT _21_ (
    .A(counter[0]),
    .Y(_04_)
  );
  NAND _22_ (
    .A(enb),
    .B(counter[1]),
    .Y(_05_)
  );
  NOT _23_ (
    .A(_05_),
    .Y(_06_)
  );
  NAND _24_ (
    .A(counter[0]),
    .B(_06_),
    .Y(_07_)
  );
  NOR _25_ (
    .A(clk_2f),
    .B(_07_),
    .Y(_08_)
  );
  NOR _26_ (
    .A(clk_f),
    .B(_08_),
    .Y(_09_)
  );
  NAND _27_ (
    .A(clk_f),
    .B(_08_),
    .Y(_10_)
  );
  NAND _28_ (
    .A(_03_),
    .B(_10_),
    .Y(_11_)
  );
  NOR _29_ (
    .A(_09_),
    .B(_11_),
    .Y(_01_)
  );
  NAND _30_ (
    .A(clk_2f),
    .B(_07_),
    .Y(_12_)
  );
  NOT _31_ (
    .A(_12_),
    .Y(_13_)
  );
  NOR _32_ (
    .A(_08_),
    .B(_13_),
    .Y(_14_)
  );
  NOR _33_ (
    .A(rst),
    .B(_14_),
    .Y(_00_)
  );
  NOR _34_ (
    .A(enb),
    .B(counter[1]),
    .Y(_15_)
  );
  NOT _35_ (
    .A(_15_),
    .Y(_16_)
  );
  NAND _36_ (
    .A(_05_),
    .B(_16_),
    .Y(_17_)
  );
  NAND _37_ (
    .A(_03_),
    .B(_17_),
    .Y(_02_[0])
  );
  NAND _38_ (
    .A(_04_),
    .B(_05_),
    .Y(_18_)
  );
  NAND _39_ (
    .A(_07_),
    .B(_18_),
    .Y(_19_)
  );
  NAND _40_ (
    .A(_03_),
    .B(_19_),
    .Y(_02_[1])
  );
  DFF _41_ (
    .C(clk_8f),
    .D(_00_),
    .Q(clk_2f)
  );
  DFF _42_ (
    .C(clk_8f),
    .D(_01_),
    .Q(clk_f)
  );
  DFF _43_ (
    .C(clk_8f),
    .D(_02_[0]),
    .Q(counter[1])
  );
  DFF _44_ (
    .C(clk_8f),
    .D(_02_[1]),
    .Q(counter[0])
  );
endmodule

gen_clk/gen_clk.v
`timescale 1ns/1ps



module gen_clk(
	clk_8f, rst, enb,
	clk_2f, clk_f	
);

    input clk_8f, rst, enb;
    output reg clk_2f, clk_f;   

    reg [0:1] counter;

    always@(posedge clk_8f) begin
        
        if(rst) begin
            counter <= 3;
            clk_2f <= 1'b0;
            clk_f <= 1'b0;
        end

        else begin
            if(enb) begin
                if (counter < 3) begin
                    counter <= counter + 'b1;  // counter de clk_2f y clk_f
                end
                else begin
                    counter <= 'b0;                         //resetear counter
                    clk_2f <= ~clk_2f;                      //clk_2f cada 4 ciclos 
                    if(~clk_2f) clk_f <= ~clk_f;            //clk_f solo la mitad
                end
            end
        end
    end


endmodule

gen_clk/bancopruebas.v
`timescale 1ns/1ps

`include "gen_clk.v"
`include "gen_clkSynth.v"
`include "probador.v"

module bancopruebas;
	/*AUTOWIRE*/
    wire		clk_8f;			// From probador of probador.v		// From conduc of gen_clk.v, ...
    wire		enb;			// From probador of probador.v
    wire		rst;			// From probador of probador.v
    
	/*AUTOREGINPUT*/
    wire			clk_2f_cond;		// To probador of probador.v
    wire			clk_2f_estruct;		// To probador of probador.v
    wire			clk_f_cond;		// To probador of probador.v
    wire		clk_f_estruct;		// To probador of probador.v
    // End of automatics
    gen_clk conduc(/*AUTOINST*/
		   // Outputs
		   .clk_2f		(clk_2f_cond),
		   .clk_f		(clk_f_cond),
		   // Inputs
		   .clk_8f		(clk_8f),
		   .rst			(rst),
		   .enb			(enb));
    gen_clkSynth estruct(/*AUTOINST*/
			 // Outputs
			 .clk_2f		(clk_2f_estruct),
			 .clk_f			(clk_f_estruct),
			 // Inputs
			 .clk_8f		(clk_8f),
			 .enb			(enb),
			 .rst			(rst));

    probador probador(/*AUTOINST*/
		      // Outputs
		      .clk_8f		(clk_8f),
		      .rst		(rst),
		      .enb		(enb),
		      // Inputs
		      .clk_2f_cond	(clk_2f_cond),
		      .clk_f_cond	(clk_f_cond),
		      .clk_2f_estruct	(clk_2f_estruct),
		      .clk_f_estruct	(clk_f_estruct));
     
    // initial begin
       
    //     $dumpfile("gen_clk.vcd")               //Dumpfile to make in current folder
    //     $dumpvars;
        
    //     clk_8f <= 0;
    //     enb <= 0;                       //                           
    //     rst <= 1;                       // relojes se resetean            
        
    //     # 10;
    //     @(posedge clk_8f)
    //         rst <= 0;
    //         enb <= 1;
        
    //     # 60;
    //     @(posedge clk_8f)
    //         enb <= 1;

    //     # 20;
    //     @(posedge clk_8f)
    //         enb <= 0;

    //     # 20;
    //     @(posedge clk_8f)
    //         rst <= 1;
                
        
    //     # 20;
    //     @(posedge clk_8f)
    //         rst <= 0;
    //         enb <= 1;
    //     $finish;
    // end

    // always # 2 clk_8f <= ~clk_8f;       //genera señal 4 ns 

endmodule

byte_stripping/cmos_cells.v
module BUF(input A,output Y);
assign Y = A;
endmodule

module NOT(input A,output Y);
assign Y = ~A;
endmodule

module NAND(input A, input B, output Y);
assign Y = ~(A & B);
endmodule

module NOR(input A, input B, output Y);
assign Y = ~(A | B);
endmodule

module DFF(input C, input D, output reg Q);
always @(posedge C)
	Q <= D;
endmodule

module DFFSR(input C, input D, input S, input R, output reg Q);
always @(posedge C, posedge S, posedge R)
	if (S)
		Q <= 1'b1;
	else if (R)
		Q <= 1'b0;
	else
		Q <= D;
endmodule

gen_clk/gen_clk.vcd
$date
	Wed May 22 18:32:36 2019
$end
$version
	Icarus Verilog
$end
$timescale
	1ps
$end
$scope module BUF $end
$var wire 1 ! A $end
$var wire 1 " Y $end
$upscope $end
$scope module DFFSR $end
$var wire 1 # C $end
$var wire 1 $ D $end
$var wire 1 % R $end
$var wire 1 & S $end
$var reg 1 ' Q $end
$upscope $end
$scope module bancopruebas $end
$var wire 1 ( rst $end
$var wire 1 ) enb $end
$var wire 1 * clk_f_estruct $end
$var wire 1 + clk_f_cond $end
$var wire 1 , clk_8f $end
$var wire 1 - clk_2f_estruct $end
$var wire 1 . clk_2f_cond $end
$scope module conduc $end
$var wire 1 ( rst $end
$var wire 1 ) enb $end
$var wire 1 , clk_8f $end
$var reg 1 . clk_2f $end
$var reg 1 + clk_f $end
$var reg 2 / counter [0:1] $end
$upscope $end
$scope module estruct $end
$var wire 1 ( rst $end
$var wire 1 ) enb $end
$var wire 2 0 counter [0:1] $end
$var wire 1 * clk_f $end
$var wire 1 , clk_8f $end
$var wire 1 - clk_2f $end
$var wire 1 1 _19_ $end
$var wire 1 2 _18_ $end
$var wire 1 3 _17_ $end
$var wire 1 4 _16_ $end
$var wire 1 5 _15_ $end
$var wire 1 6 _14_ $end
$var wire 1 7 _13_ $end
$var wire 1 8 _12_ $end
$var wire 1 9 _11_ $end
$var wire 1 : _10_ $end
$var wire 1 ; _09_ $end
$var wire 1 < _08_ $end
$var wire 1 = _07_ $end
$var wire 1 > _06_ $end
$var wire 1 ? _05_ $end
$var wire 1 @ _04_ $end
$var wire 1 A _03_ $end
$var wire 2 B _02_ [1:0] $end
$var wire 1 C _01_ $end
$var wire 1 D _00_ $end
$scope module _20_ $end
$var wire 1 A Y $end
$var wire 1 ( A $end
$upscope $end
$scope module _21_ $end
$var wire 1 E A $end
$var wire 1 @ Y $end
$upscope $end
$scope module _22_ $end
$var wire 1 F B $end
$var wire 1 ? Y $end
$var wire 1 ) A $end
$upscope $end
$scope module _23_ $end
$var wire 1 ? A $end
$var wire 1 > Y $end
$upscope $end
$scope module _24_ $end
$var wire 1 G A $end
$var wire 1 > B $end
$var wire 1 = Y $end
$upscope $end
$scope module _25_ $end
$var wire 1 = B $end
$var wire 1 < Y $end
$var wire 1 - A $end
$upscope $end
$scope module _26_ $end
$var wire 1 < B $end
$var wire 1 ; Y $end
$var wire 1 * A $end
$upscope $end
$scope module _27_ $end
$var wire 1 < B $end
$var wire 1 : Y $end
$var wire 1 * A $end
$upscope $end
$scope module _28_ $end
$var wire 1 A A $end
$var wire 1 : B $end
$var wire 1 9 Y $end
$upscope $end
$scope module _29_ $end
$var wire 1 ; A $end
$var wire 1 9 B $end
$var wire 1 C Y $end
$upscope $end
$scope module _30_ $end
$var wire 1 = B $end
$var wire 1 8 Y $end
$var wire 1 - A $end
$upscope $end
$scope module _31_ $end
$var wire 1 8 A $end
$var wire 1 7 Y $end
$upscope $end
$scope module _32_ $end
$var wire 1 < A $end
$var wire 1 7 B $end
$var wire 1 6 Y $end
$upscope $end
$scope module _33_ $end
$var wire 1 6 B $end
$var wire 1 D Y $end
$var wire 1 ( A $end
$upscope $end
$scope module _34_ $end
$var wire 1 H B $end
$var wire 1 5 Y $end
$var wire 1 ) A $end
$upscope $end
$scope module _35_ $end
$var wire 1 5 A $end
$var wire 1 4 Y $end
$upscope $end
$scope module _36_ $end
$var wire 1 ? A $end
$var wire 1 4 B $end
$var wire 1 3 Y $end
$upscope $end
$scope module _37_ $end
$var wire 1 A A $end
$var wire 1 3 B $end
$var wire 1 I Y $end
$upscope $end
$scope module _38_ $end
$var wire 1 @ A $end
$var wire 1 ? B $end
$var wire 1 2 Y $end
$upscope $end
$scope module _39_ $end
$var wire 1 = A $end
$var wire 1 2 B $end
$var wire 1 1 Y $end
$upscope $end
$scope module _40_ $end
$var wire 1 A A $end
$var wire 1 1 B $end
$var wire 1 J Y $end
$upscope $end
$scope module _41_ $end
$var wire 1 D D $end
$var wire 1 , C $end
$var reg 1 - Q $end
$upscope $end
$scope module _42_ $end
$var wire 1 C D $end
$var wire 1 , C $end
$var reg 1 * Q $end
$upscope $end
$scope module _43_ $end
$var wire 1 K D $end
$var wire 1 , C $end
$var reg 1 L Q $end
$upscope $end
$scope module _44_ $end
$var wire 1 M D $end
$var wire 1 , C $end
$var reg 1 N Q $end
$upscope $end
$upscope $end
$scope module probador $end
$var wire 1 . clk_2f_cond $end
$var wire 1 - clk_2f_estruct $end
$var wire 1 + clk_f_cond $end
$var wire 1 * clk_f_estruct $end
$var reg 1 , clk_8f $end
$var reg 1 ) enb $end
$var reg 1 O f2_cond $end
$var reg 1 P f2_estruct $end
$var reg 1 Q f_cond $end
$var reg 1 R f_estruct $end
$var reg 1 ( rst $end
$upscope $end
$upscope $end
$enddefinitions $end
#0
$dumpvars
xR
xQ
xP
xO
xN
1M
xL
1K
1J
1I
xH
xG
xF
xE
0D
0C
b11 B
0A
x@
1?
0>
1=
0<
x;
1:
19
x8
x7
x6
x5
x4
x3
x2
x1
bx 0
bx /
x.
x-
0,
x+
x*
0)
1(
x'
z&
z%
z$
z#
z"
z!
$end
#2000
03
01
16
14
12
07
05
18
1;
0@
1H
1F
1G
1E
0+
0.
b11 /
0-
0*
1L
b11 0
1N
1,
#4000
0,
#6000
0R
0P
0Q
0O
1,
#8000
0,
#10000
1C
1D
0M
0;
06
0J
1<
11
0K
b0 B
0I
0=
13
1>
09
0?
1A
1)
0(
1,
#12000
0,
#14000
1K
b1 B
1I
17
1C
1D
08
03
02
0>
09
06
1=
1?
1@
1:
0<
0G
0E
0H
0F
0N
b0 0
0L
1*
1-
1+
1.
b0 /
1,
#16000
0,
#18000
1M
1J
0K
b10 B
0I
01
13
12
1>
0?
1H
1F
b1 /
b1 0
1L
1R
1P
1Q
1O
1,
#20000
0,
#22000
1D
06
1M
1K
1J
b11 B
1I
17
08
01
03
0>
1=
1?
0@
1G
1E
0H
0F
1N
b10 0
0L
b10 /
1,
#24000
0,
#26000
0D
16
0M
0J
07
18
11
0K
b0 B
0I
0=
13
1>
0?
1H
1F
b11 /
b11 0
1L
1,
#28000
0,
#30000
1K
1C
b1 B
1I
09
0D
03
02
0>
1:
16
1=
1?
1@
0<
0G
0E
0H
0F
0N
b0 0
0L
0-
0.
b0 /
1,
#32000
0,
#34000
1M
1J
0K
b10 B
0I
01
13
12
1>
0?
1H
1F
b1 /
b1 0
1L
0P
0O
1,
#36000
0,
#38000
1C
09
0D
1M
1K
1:
16
1J
b11 B
1I
0<
01
03
0>
1=
1?
0@
1G
1E
0H
0F
1N
b10 0
0L
b10 /
1,
#40000
0,
#42000
0C
19
1D
0M
0:
06
0J
1<
11
0K
b0 B
0I
0=
13
1>
0?
1H
1F
b11 /
b11 0
1L
1,
#44000
0,
#46000
1K
b1 B
1I
17
1D
08
03
02
0>
09
1;
06
1=
1?
1@
1:
0<
0G
0E
0H
0F
0N
b0 0
0L
0*
1-
0+
1.
b0 /
1,
#48000
0,
#50000
1M
1J
0K
b10 B
0I
01
13
12
1>
0?
1H
1F
b1 /
b1 0
1L
0R
1P
0Q
1O
1,
#52000
0,
#54000
1D
06
1M
1K
1J
b11 B
1I
17
08
01
03
0>
1=
1?
0@
1G
1E
0H
0F
1N
b10 0
0L
b10 /
1,
#56000
0,
#58000
0D
16
0M
0J
07
18
11
0K
b0 B
0I
0=
13
1>
0?
1H
1F
b11 /
b11 0
1L
1,
#60000
0,
#62000
1K
b1 B
1I
0C
0D
03
02
0>
1;
16
1=
1?
1@
0<
0G
0E
0H
0F
0N
b0 0
0L
0-
0.
b0 /
1,
#64000
0,
#66000
1M
1J
0K
b10 B
0I
01
13
12
1>
0?
1H
1F
b1 /
b1 0
1L
0P
0O
1,
#68000
0,
#70000
0C
0D
1M
1K
1;
16
1J
b11 B
1I
0<
01
03
0>
1=
1?
0@
1G
1E
0H
0F
1N
b10 0
0L
b10 /
1,
#72000
0,
#74000
1C
1D
0M
0;
06
0J
1<
11
0K
b0 B
0I
0=
13
1>
0?
1H
1F
b11 /
b11 0
1L
1,
#76000
0,
#78000
1K
b1 B
1I
17
1C
1D
08
03
02
0>
09
06
1=
1?
1@
1:
0<
0G
0E
0H
0F
0N
b0 0
0L
1*
1-
1+
1.
b0 /
1,
#80000
0,
#82000
1M
1J
0K
b10 B
0I
01
13
12
1>
0?
1H
1F
b1 /
b1 0
1L
1R
1P
1Q
1O
1,
#84000
0,
#86000
1D
06
1M
1K
1J
b11 B
1I
17
08
01
03
0>
1=
1?
0@
1G
1E
0H
0F
1N
b10 0
0L
b10 /
1,
#88000
0,
#90000
1K
b11 B
1I
03
14
05
1H
1F
b11 /
b11 0
1L
0)
1,
#92000
0,
#94000
1,
#96000
0,
#98000
1,
#100000
0,
#102000
1,
#104000
0,
#106000
1,
#108000
0,
#110000
0C
19
0D
0A
1(
1,
#112000
0,
#114000
16
07
18
1;
0+
0.
0-
0*
1,
#116000
0,
#118000
0R
0P
0Q
0O
1,
#120000
0,
#122000
1,
#124000
0,
#126000
1,
#128000
0,
#130000
1C
1D
0M
0;
06
0J
1<
11
0K
b0 B
0I
0=
13
1>
09
0?
1A
1)
0(
1,
